{
"meta":{"test_sets":[],"test_metrics":[],"learn_metrics":[{"best_value":"Min","name":"Logloss"}],"launch_mode":"Train","parameters":"","iteration_count":1000,"learn_sets":["learn"],"name":"experiment"},
"iterations":[
{"learn":[0.6903757388],"iteration":0,"passed_time":0.1507655472,"remaining_time":150.6147816},
{"learn":[0.686723911],"iteration":1,"passed_time":0.1549483505,"remaining_time":77.31922688},
{"learn":[0.6838728742],"iteration":2,"passed_time":0.1582069812,"remaining_time":52.57745343},
{"learn":[0.6816122849],"iteration":3,"passed_time":0.1618513286,"remaining_time":40.30098083},
{"learn":[0.6790972844],"iteration":4,"passed_time":0.1648684579,"remaining_time":32.80882312},
{"learn":[0.675528173],"iteration":5,"passed_time":0.1677153709,"remaining_time":27.78484645},
{"learn":[0.6728487424],"iteration":6,"passed_time":0.1704515924,"remaining_time":24.17977589},
{"learn":[0.6678854501],"iteration":7,"passed_time":0.1731497372,"remaining_time":21.47056741},
{"learn":[0.6651952502],"iteration":8,"passed_time":0.1761147704,"remaining_time":19.39219305},
{"learn":[0.6624195249],"iteration":9,"passed_time":0.1779793122,"remaining_time":17.61995191},
{"learn":[0.6594150771],"iteration":10,"passed_time":0.1797702147,"remaining_time":16.16297658},
{"learn":[0.6565918292],"iteration":11,"passed_time":0.1816004768,"remaining_time":14.95177259},
{"learn":[0.6529839135],"iteration":12,"passed_time":0.1832250342,"remaining_time":13.91100837},
{"learn":[0.6496198116],"iteration":13,"passed_time":0.1847523863,"remaining_time":13.01184663},
{"learn":[0.6470951512],"iteration":14,"passed_time":0.1863045867,"remaining_time":12.23400119},
{"learn":[0.6436453879],"iteration":15,"passed_time":0.187786475,"remaining_time":11.54886821},
{"learn":[0.6420548811],"iteration":16,"passed_time":0.1894604879,"remaining_time":10.95527409},
{"learn":[0.6405850162],"iteration":17,"passed_time":0.190599548,"remaining_time":10.39826423},
{"learn":[0.6380125336],"iteration":18,"passed_time":0.1917823892,"remaining_time":9.902027568},
{"learn":[0.6355715559],"iteration":19,"passed_time":0.1928954193,"remaining_time":9.451875548},
{"learn":[0.6317105533],"iteration":20,"passed_time":0.193870215,"remaining_time":9.038044787},
{"learn":[0.6291222646],"iteration":21,"passed_time":0.194868256,"remaining_time":8.662779742},
{"learn":[0.626721621],"iteration":22,"passed_time":0.1957503112,"remaining_time":8.315132786},
{"learn":[0.6247584476],"iteration":23,"passed_time":0.1967273596,"remaining_time":8.000245956},
{"learn":[0.6211021477],"iteration":24,"passed_time":0.197701297,"remaining_time":7.710350582},
{"learn":[0.6182285673],"iteration":25,"passed_time":0.1986960328,"remaining_time":7.443459075},
{"learn":[0.6161319866],"iteration":26,"passed_time":0.1996346869,"remaining_time":7.194242606},
{"learn":[0.6136830075],"iteration":27,"passed_time":0.2005739535,"remaining_time":6.962781527},
{"learn":[0.6114868426],"iteration":28,"passed_time":0.2015070548,"remaining_time":6.747012077},
{"learn":[0.6082155604],"iteration":29,"passed_time":0.2024397504,"remaining_time":6.54555193},
{"learn":[0.6062561291],"iteration":30,"passed_time":0.2034209354,"remaining_time":6.358544722},
{"learn":[0.6031715726],"iteration":31,"passed_time":0.2044947326,"remaining_time":6.185965663},
{"learn":[0.6019479228],"iteration":32,"passed_time":0.2054250228,"remaining_time":6.01957567},
{"learn":[0.6004939623],"iteration":33,"passed_time":0.2063419724,"remaining_time":5.862539569},
{"learn":[0.5967281609],"iteration":34,"passed_time":0.2072489438,"remaining_time":5.714149452},
{"learn":[0.5953964421],"iteration":35,"passed_time":0.2081988694,"remaining_time":5.575103059},
{"learn":[0.593732434],"iteration":36,"passed_time":0.2091143079,"remaining_time":5.442623744},
{"learn":[0.5917383241],"iteration":37,"passed_time":0.2100417149,"remaining_time":5.317371834},
{"learn":[0.5904984113],"iteration":38,"passed_time":0.2109509868,"remaining_time":5.198048674},
{"learn":[0.5879671648],"iteration":39,"passed_time":0.211864006,"remaining_time":5.084736143},
{"learn":[0.5856530949],"iteration":40,"passed_time":0.2127819687,"remaining_time":4.977022146},
{"learn":[0.5823131982],"iteration":41,"passed_time":0.2137434419,"remaining_time":4.875386128},
{"learn":[0.5814874973],"iteration":42,"passed_time":0.2146563301,"remaining_time":4.777351348},
{"learn":[0.5788570882],"iteration":43,"passed_time":0.2155709935,"remaining_time":4.683769768},
{"learn":[0.5773824954],"iteration":44,"passed_time":0.2164851879,"remaining_time":4.594296766},
{"learn":[0.5758389696],"iteration":45,"passed_time":0.217466718,"remaining_time":4.51007063},
{"learn":[0.573648984],"iteration":46,"passed_time":0.2185753363,"remaining_time":4.431963735},
{"learn":[0.5721713753],"iteration":47,"passed_time":0.2198338825,"remaining_time":4.360038669},
{"learn":[0.5692987607],"iteration":48,"passed_time":0.2208927884,"remaining_time":4.287123301},
{"learn":[0.5668341879],"iteration":49,"passed_time":0.221812663,"remaining_time":4.214440596},
{"learn":[0.5650900515],"iteration":50,"passed_time":0.2227332802,"remaining_time":4.144585939},
{"learn":[0.563527869],"iteration":51,"passed_time":0.2236454704,"remaining_time":4.07722896},
{"learn":[0.5612693198],"iteration":52,"passed_time":0.2245553019,"remaining_time":4.012337186},
{"learn":[0.5588646827],"iteration":53,"passed_time":0.2255057456,"remaining_time":3.950526581},
{"learn":[0.5572201305],"iteration":54,"passed_time":0.2265046838,"remaining_time":3.891762294},
{"learn":[0.5557867023],"iteration":55,"passed_time":0.2275212826,"remaining_time":3.835358764},
{"learn":[0.5528665807],"iteration":56,"passed_time":0.2285759531,"remaining_time":3.781528487},
{"learn":[0.5505172306],"iteration":57,"passed_time":0.2295806085,"remaining_time":3.728705744},
{"learn":[0.5483576329],"iteration":58,"passed_time":0.2305780919,"remaining_time":3.677525161},
{"learn":[0.5462825194],"iteration":59,"passed_time":0.2315909321,"remaining_time":3.628257936},
{"learn":[0.5436284294],"iteration":60,"passed_time":0.2330134579,"remaining_time":3.586879294},
{"learn":[0.5414614277],"iteration":61,"passed_time":0.2342589292,"remaining_time":3.544110897},
{"learn":[0.5398039483],"iteration":62,"passed_time":0.2356022287,"remaining_time":3.504115687},
{"learn":[0.5381923936],"iteration":63,"passed_time":0.2365379146,"remaining_time":3.459367001},
{"learn":[0.536429497],"iteration":64,"passed_time":0.2374416759,"remaining_time":3.415507184},
{"learn":[0.5345230072],"iteration":65,"passed_time":0.2383596704,"remaining_time":3.373150487},
{"learn":[0.5329511026],"iteration":66,"passed_time":0.2392819122,"remaining_time":3.332089911},
{"learn":[0.5303431745],"iteration":67,"passed_time":0.2402391042,"remaining_time":3.292688899},
{"learn":[0.5267025924],"iteration":68,"passed_time":0.2411390119,"remaining_time":3.253629276},
{"learn":[0.5251143061],"iteration":69,"passed_time":0.2420654974,"remaining_time":3.216013036},
{"learn":[0.5242314787],"iteration":70,"passed_time":0.2429596692,"remaining_time":3.179007502},
{"learn":[0.5227145318],"iteration":71,"passed_time":0.2438792768,"remaining_time":3.143332901},
{"learn":[0.5214172354],"iteration":72,"passed_time":0.2448157607,"remaining_time":3.108824797},
{"learn":[0.5192475432],"iteration":73,"passed_time":0.2457567196,"remaining_time":3.075280031},
{"learn":[0.5173078932],"iteration":74,"passed_time":0.2466647502,"remaining_time":3.042198586},
{"learn":[0.515888868],"iteration":75,"passed_time":0.2479877423,"remaining_time":3.015008867},
{"learn":[0.514497288],"iteration":76,"passed_time":0.2494659166,"remaining_time":2.990351182},
{"learn":[0.5125942774],"iteration":77,"passed_time":0.2504050628,"remaining_time":2.959916256},
{"learn":[0.5104219696],"iteration":78,"passed_time":0.2513194896,"remaining_time":2.929939872},
{"learn":[0.5090847146],"iteration":79,"passed_time":0.2522256809,"remaining_time":2.90059533},
{"learn":[0.5072331798],"iteration":80,"passed_time":0.2531412614,"remaining_time":2.872059497},
{"learn":[0.5054144581],"iteration":81,"passed_time":0.2540671984,"remaining_time":2.844313269},
{"learn":[0.5037352699],"iteration":82,"passed_time":0.2550152931,"remaining_time":2.817458118},
{"learn":[0.501793207],"iteration":83,"passed_time":0.2559156669,"remaining_time":2.790699415},
{"learn":[0.5006924615],"iteration":84,"passed_time":0.256839682,"remaining_time":2.764803635},
{"learn":[0.4999422692],"iteration":85,"passed_time":0.2578337487,"remaining_time":2.740233096},
{"learn":[0.4982089248],"iteration":86,"passed_time":0.258850622,"remaining_time":2.716443883},
{"learn":[0.4964108454],"iteration":87,"passed_time":0.2598677419,"remaining_time":2.693174779},
{"learn":[0.494037817],"iteration":88,"passed_time":0.2608870712,"remaining_time":2.670428336},
{"learn":[0.4928153431],"iteration":89,"passed_time":0.2620571685,"remaining_time":2.649689148},
{"learn":[0.4902487719],"iteration":90,"passed_time":0.2631090381,"remaining_time":2.628199073},
{"learn":[0.4882872692],"iteration":91,"passed_time":0.2643564141,"remaining_time":2.60908287},
{"learn":[0.4865957455],"iteration":92,"passed_time":0.2653519287,"remaining_time":2.587894616},
{"learn":[0.4853123927],"iteration":93,"passed_time":0.2664344564,"remaining_time":2.567974654},
{"learn":[0.4830582307],"iteration":94,"passed_time":0.2673445702,"remaining_time":2.5468088},
{"learn":[0.4819440816],"iteration":95,"passed_time":0.2682575455,"remaining_time":2.526091886},
{"learn":[0.4809089203],"iteration":96,"passed_time":0.2691658524,"remaining_time":2.505739842},
{"learn":[0.4795953127],"iteration":97,"passed_time":0.2701116392,"remaining_time":2.486129577},
{"learn":[0.4783761567],"iteration":98,"passed_time":0.271045996,"remaining_time":2.466792348},
{"learn":[0.4775261379],"iteration":99,"passed_time":0.2719676272,"remaining_time":2.447708645},
{"learn":[0.4753925913],"iteration":100,"passed_time":0.2728735226,"remaining_time":2.428844523},
{"learn":[0.4736863605],"iteration":101,"passed_time":0.2737883294,"remaining_time":2.410410979},
{"learn":[0.4724509855],"iteration":102,"passed_time":0.274706209,"remaining_time":2.392344364},
{"learn":[0.4718229484],"iteration":103,"passed_time":0.2756230008,"remaining_time":2.374598161},
{"learn":[0.4705257216],"iteration":104,"passed_time":0.2771387642,"remaining_time":2.362278037},
{"learn":[0.4699276712],"iteration":105,"passed_time":0.2783441582,"remaining_time":2.347544127},
{"learn":[0.4686894017],"iteration":106,"passed_time":0.2794485953,"remaining_time":2.33222052},
{"learn":[0.467122838],"iteration":107,"passed_time":0.2805019378,"remaining_time":2.316738227},
{"learn":[0.4650872211],"iteration":108,"passed_time":0.2815958265,"remaining_time":2.301852123},
{"learn":[0.4639199946],"iteration":109,"passed_time":0.2826466441,"remaining_time":2.286868302},
{"learn":[0.4626143383],"iteration":110,"passed_time":0.2836989955,"remaining_time":2.272147811},
{"learn":[0.462482127],"iteration":111,"passed_time":0.2845323658,"remaining_time":2.255935186},
{"learn":[0.4612499719],"iteration":112,"passed_time":0.2860434322,"remaining_time":2.245314375},
{"learn":[0.4597711646],"iteration":113,"passed_time":0.2870267153,"remaining_time":2.230751489},
{"learn":[0.4580735194],"iteration":114,"passed_time":0.2879368052,"remaining_time":2.215861501},
{"learn":[0.4573517829],"iteration":115,"passed_time":0.288869464,"remaining_time":2.201384536},
{"learn":[0.4554949026],"iteration":116,"passed_time":0.2897752214,"remaining_time":2.186936072},
{"learn":[0.4547759538],"iteration":117,"passed_time":0.290684636,"remaining_time":2.172744483},
{"learn":[0.4539626154],"iteration":118,"passed_time":0.2919983577,"remaining_time":2.161769354},
{"learn":[0.4531694431],"iteration":119,"passed_time":0.2929365929,"remaining_time":2.148201681},
{"learn":[0.4519098684],"iteration":120,"passed_time":0.2938364716,"remaining_time":2.13456412},
{"learn":[0.4503569366],"iteration":121,"passed_time":0.2947635956,"remaining_time":2.12133145},
{"learn":[0.4483592119],"iteration":122,"passed_time":0.2956818645,"remaining_time":2.108235733},
{"learn":[0.4469293826],"iteration":123,"passed_time":0.2965948587,"remaining_time":2.095299163},
{"learn":[0.4465020734],"iteration":124,"passed_time":0.2975077544,"remaining_time":2.082554281},
{"learn":[0.4458238243],"iteration":125,"passed_time":0.2984976413,"remaining_time":2.070531258},
{"learn":[0.444519247],"iteration":126,"passed_time":0.2994081791,"remaining_time":2.058136538},
{"learn":[0.4431663082],"iteration":127,"passed_time":0.3003437426,"remaining_time":2.046091746},
{"learn":[0.4415744417],"iteration":128,"passed_time":0.3013080309,"remaining_time":2.034413139},
{"learn":[0.4405812203],"iteration":129,"passed_time":0.3022306706,"remaining_time":2.022620642},
{"learn":[0.4392418011],"iteration":130,"passed_time":0.303139986,"remaining_time":2.010905709},
{"learn":[0.4371294899],"iteration":131,"passed_time":0.3040662581,"remaining_time":1.999466},
{"learn":[0.4366313332],"iteration":132,"passed_time":0.3049652693,"remaining_time":1.98800668},
{"learn":[0.4355030606],"iteration":133,"passed_time":0.3060397196,"remaining_time":1.977838785},
{"learn":[0.4339300888],"iteration":134,"passed_time":0.3069571042,"remaining_time":1.966799223},
{"learn":[0.4324456107],"iteration":135,"passed_time":0.3078683622,"remaining_time":1.955869595},
{"learn":[0.4308986427],"iteration":136,"passed_time":0.308777239,"remaining_time":1.945071221},
{"learn":[0.4296221655],"iteration":137,"passed_time":0.3096795421,"remaining_time":1.934375111},
{"learn":[0.4283895353],"iteration":138,"passed_time":0.3105866206,"remaining_time":1.923849499},
{"learn":[0.4273183318],"iteration":139,"passed_time":0.3115100858,"remaining_time":1.913561955},
{"learn":[0.4258213511],"iteration":140,"passed_time":0.3124259397,"remaining_time":1.903360867},
{"learn":[0.4251421253],"iteration":141,"passed_time":0.3134220541,"remaining_time":1.89377551},
{"learn":[0.4235727267],"iteration":142,"passed_time":0.3143365876,"remaining_time":1.883821368},
{"learn":[0.4225979212],"iteration":143,"passed_time":0.3152447749,"remaining_time":1.873955051},
{"learn":[0.4212144587],"iteration":144,"passed_time":0.31616836,"remaining_time":1.864303088},
{"learn":[0.4202252043],"iteration":145,"passed_time":0.317080002,"remaining_time":1.854700834},
{"learn":[0.4192685161],"iteration":146,"passed_time":0.3179916065,"remaining_time":1.845216601},
{"learn":[0.4176372353],"iteration":147,"passed_time":0.3190000813,"remaining_time":1.836405873},
{"learn":[0.416309328],"iteration":148,"passed_time":0.3200023709,"remaining_time":1.827664548},
{"learn":[0.4157811057],"iteration":149,"passed_time":0.3210374852,"remaining_time":1.819212416},
{"learn":[0.4144879751],"iteration":150,"passed_time":0.3220432213,"remaining_time":1.810693343},
{"learn":[0.4130152053],"iteration":151,"passed_time":0.3230625431,"remaining_time":1.802348925},
{"learn":[0.4120492061],"iteration":152,"passed_time":0.3240595991,"remaining_time":1.793976996},
{"learn":[0.4113821496],"iteration":153,"passed_time":0.3250566703,"remaining_time":1.785700929},
{"learn":[0.4097656086],"iteration":154,"passed_time":0.3260393482,"remaining_time":1.777440317},
{"learn":[0.4092718241],"iteration":155,"passed_time":0.3271763441,"remaining_time":1.770107913},
{"learn":[0.4081542997],"iteration":156,"passed_time":0.32828436,"remaining_time":1.762698825},
{"learn":[0.4073555759],"iteration":157,"passed_time":0.3293701811,"remaining_time":1.755251218},
{"learn":[0.4067942987],"iteration":158,"passed_time":0.3302974549,"remaining_time":1.747045029},
{"learn":[0.405604493],"iteration":159,"passed_time":0.3312018314,"remaining_time":1.738809615},
{"learn":[0.4048673761],"iteration":160,"passed_time":0.3321247506,"remaining_time":1.730761899},
{"learn":[0.4040869085],"iteration":161,"passed_time":0.3330419,"remaining_time":1.722772297},
{"learn":[0.4033452283],"iteration":162,"passed_time":0.3339759878,"remaining_time":1.714956452},
{"learn":[0.402175823],"iteration":163,"passed_time":0.3348861797,"remaining_time":1.707102721},
{"learn":[0.4013792405],"iteration":164,"passed_time":0.3358080446,"remaining_time":1.699392226},
{"learn":[0.4005237835],"iteration":165,"passed_time":0.3367601297,"remaining_time":1.69191535},
{"learn":[0.3988208323],"iteration":166,"passed_time":0.33770399,"remaining_time":1.684475591},
{"learn":[0.3976669544],"iteration":167,"passed_time":0.3386327742,"remaining_time":1.677038501},
{"learn":[0.3961404449],"iteration":168,"passed_time":0.339544197,"remaining_time":1.669593063},
{"learn":[0.3950893022],"iteration":169,"passed_time":0.3404428749,"remaining_time":1.662162271},
{"learn":[0.3945274784],"iteration":170,"passed_time":0.341350321,"remaining_time":1.654850386},
{"learn":[0.3933898437],"iteration":171,"passed_time":0.3424911844,"remaining_time":1.648736632},
{"learn":[0.392540605],"iteration":172,"passed_time":0.3438751533,"remaining_time":1.643842496},
{"learn":[0.3910608949],"iteration":173,"passed_time":0.3452289419,"remaining_time":1.638845437},
{"learn":[0.3897957715],"iteration":174,"passed_time":0.346582152,"remaining_time":1.633887288},
{"learn":[0.3893113721],"iteration":175,"passed_time":0.3475584934,"remaining_time":1.627205673},
{"learn":[0.3885170187],"iteration":176,"passed_time":0.3484810834,"remaining_time":1.620338597},
{"learn":[0.3875428423],"iteration":177,"passed_time":0.3494191491,"remaining_time":1.613609778},
{"learn":[0.3868721508],"iteration":178,"passed_time":0.3504391894,"remaining_time":1.607321645},
{"learn":[0.3868306834],"iteration":179,"passed_time":0.3511196341,"remaining_time":1.599545},
{"learn":[0.385721548],"iteration":180,"passed_time":0.3521486368,"remaining_time":1.593423942},
{"learn":[0.3838101584],"iteration":181,"passed_time":0.3531487605,"remaining_time":1.587229045},
{"learn":[0.3828663413],"iteration":182,"passed_time":0.3541228903,"remaining_time":1.580974871},
{"learn":[0.3820330453],"iteration":183,"passed_time":0.3551344471,"remaining_time":1.57494407},
{"learn":[0.3806619575],"iteration":184,"passed_time":0.3561153101,"remaining_time":1.568832312},
{"learn":[0.379093391],"iteration":185,"passed_time":0.3575623406,"remaining_time":1.564815835},
{"learn":[0.3782765578],"iteration":186,"passed_time":0.3585080324,"remaining_time":1.558647221},
{"learn":[0.3775127102],"iteration":187,"passed_time":0.359423507,"remaining_time":1.552403658},
{"learn":[0.3763851112],"iteration":188,"passed_time":0.3603367268,"remaining_time":1.546206801},
{"learn":[0.3755882163],"iteration":189,"passed_time":0.3617614959,"remaining_time":1.542246377},
{"learn":[0.3750447159],"iteration":190,"passed_time":0.3630040429,"remaining_time":1.537540684},
{"learn":[0.3745715007],"iteration":191,"passed_time":0.3643001581,"remaining_time":1.533096499},
{"learn":[0.3736185155],"iteration":192,"passed_time":0.3653238932,"remaining_time":1.52754602},
{"learn":[0.372411198],"iteration":193,"passed_time":0.3662451154,"remaining_time":1.521616304},
{"learn":[0.3710836122],"iteration":194,"passed_time":0.3671514805,"remaining_time":1.515676625},
{"learn":[0.3696337001],"iteration":195,"passed_time":0.3680521191,"remaining_time":1.509764815},
{"learn":[0.3689626381],"iteration":196,"passed_time":0.3689667774,"remaining_time":1.503961027},
{"learn":[0.3685591119],"iteration":197,"passed_time":0.3698844903,"remaining_time":1.498218996},
{"learn":[0.36777939],"iteration":198,"passed_time":0.3707850336,"remaining_time":1.492456341},
{"learn":[0.3668459408],"iteration":199,"passed_time":0.371688802,"remaining_time":1.486755208},
{"learn":[0.3660205394],"iteration":200,"passed_time":0.3725962831,"remaining_time":1.481116568},
{"learn":[0.365523503],"iteration":201,"passed_time":0.3735240298,"remaining_time":1.475604831},
{"learn":[0.3644838337],"iteration":202,"passed_time":0.3745523994,"remaining_time":1.470533312},
{"learn":[0.3635364925],"iteration":203,"passed_time":0.3759520971,"remaining_time":1.46695034},
{"learn":[0.362628151],"iteration":204,"passed_time":0.37705835,"remaining_time":1.462250675},
{"learn":[0.362037258],"iteration":205,"passed_time":0.3780560609,"remaining_time":1.457167536},
{"learn":[0.3611834362],"iteration":206,"passed_time":0.3789946989,"remaining_time":1.451897566},
{"learn":[0.3604072467],"iteration":207,"passed_time":0.3799814994,"remaining_time":1.446852632},
{"learn":[0.359127398],"iteration":208,"passed_time":0.3809762392,"remaining_time":1.44187658},
{"learn":[0.358987662],"iteration":209,"passed_time":0.3817849264,"remaining_time":1.436238533},
{"learn":[0.3584835603],"iteration":210,"passed_time":0.3827969772,"remaining_time":1.431406706},
{"learn":[0.3583243409],"iteration":211,"passed_time":0.3837015461,"remaining_time":1.426211407},
{"learn":[0.3571109828],"iteration":212,"passed_time":0.3846858088,"remaining_time":1.421350852},
{"learn":[0.3558713881],"iteration":213,"passed_time":0.385679095,"remaining_time":1.416559667},
{"learn":[0.3554821191],"iteration":214,"passed_time":0.3866866889,"remaining_time":1.41185605},
{"learn":[0.3545561994],"iteration":215,"passed_time":0.3878279072,"remaining_time":1.407671663},
{"learn":[0.3537767479],"iteration":216,"passed_time":0.3887440559,"remaining_time":1.402703206},
{"learn":[0.3529508492],"iteration":217,"passed_time":0.3899947249,"remaining_time":1.398971903},
{"learn":[0.3519034566],"iteration":218,"passed_time":0.3918670167,"remaining_time":1.397480092},
{"learn":[0.350857037],"iteration":219,"passed_time":0.3935616443,"remaining_time":1.395354921},
{"learn":[0.3500583152],"iteration":220,"passed_time":0.39485704,"remaining_time":1.391826399},
{"learn":[0.3495673496],"iteration":221,"passed_time":0.3962662187,"remaining_time":1.388716748},
{"learn":[0.3488884931],"iteration":222,"passed_time":0.3977123666,"remaining_time":1.385751161},
{"learn":[0.3484236485],"iteration":223,"passed_time":0.3987471001,"remaining_time":1.381373883},
{"learn":[0.3477470666],"iteration":224,"passed_time":0.4001223981,"remaining_time":1.378199371},
{"learn":[0.3467185974],"iteration":225,"passed_time":0.4011935526,"remaining_time":1.373999158},
{"learn":[0.3462210859],"iteration":226,"passed_time":0.4024117385,"remaining_time":1.370327197},
{"learn":[0.345375537],"iteration":227,"passed_time":0.4036613561,"remaining_time":1.366783188},
{"learn":[0.3449741659],"iteration":228,"passed_time":0.4048948222,"remaining_time":1.363204838},
{"learn":[0.3442801546],"iteration":229,"passed_time":0.4061785971,"remaining_time":1.359815303},
{"learn":[0.3439371458],"iteration":230,"passed_time":0.4074883592,"remaining_time":1.356530512},
{"learn":[0.3435333099],"iteration":231,"passed_time":0.4088295826,"remaining_time":1.353366894},
{"learn":[0.3428922361],"iteration":232,"passed_time":0.4098459859,"remaining_time":1.349149662},
{"learn":[0.3422421089],"iteration":233,"passed_time":0.4110902192,"remaining_time":1.345705589},
{"learn":[0.3412302021],"iteration":234,"passed_time":0.4128768723,"remaining_time":1.344045989},
{"learn":[0.3405089822],"iteration":235,"passed_time":0.4140494966,"remaining_time":1.340397523},
{"learn":[0.3400394029],"iteration":236,"passed_time":0.4152706924,"remaining_time":1.336926322},
{"learn":[0.3395774599],"iteration":237,"passed_time":0.4164942418,"remaining_time":1.333481564},
{"learn":[0.3388386129],"iteration":238,"passed_time":0.4179247108,"remaining_time":1.330714246},
{"learn":[0.3378967902],"iteration":239,"passed_time":0.4190762551,"remaining_time":1.327074808},
{"learn":[0.3376296667],"iteration":240,"passed_time":0.4205348371,"remaining_time":1.324422993},
{"learn":[0.3362805996],"iteration":241,"passed_time":0.4219902233,"remaining_time":1.32177103},
{"learn":[0.3354440875],"iteration":242,"passed_time":0.4235574999,"remaining_time":1.319477479},
{"learn":[0.3348009151],"iteration":243,"passed_time":0.42498534,"remaining_time":1.316757857},
{"learn":[0.3343198006],"iteration":244,"passed_time":0.4261226036,"remaining_time":1.313153329},
{"learn":[0.3336495476],"iteration":245,"passed_time":0.4272791425,"remaining_time":1.309627941},
{"learn":[0.3322490887],"iteration":246,"passed_time":0.4288227031,"remaining_time":1.307301601},
{"learn":[0.3313107334],"iteration":247,"passed_time":0.4301857635,"remaining_time":1.304434251},
{"learn":[0.3307785203],"iteration":248,"passed_time":0.4314058704,"remaining_time":1.301147826},
{"learn":[0.3294697369],"iteration":249,"passed_time":0.4324373834,"remaining_time":1.29731215},
{"learn":[0.328678336],"iteration":250,"passed_time":0.4335969672,"remaining_time":1.29388099},
{"learn":[0.3280941035],"iteration":251,"passed_time":0.4352335702,"remaining_time":1.291883772},
{"learn":[0.3277100842],"iteration":252,"passed_time":0.4362960136,"remaining_time":1.288194159},
{"learn":[0.3264979144],"iteration":253,"passed_time":0.4378293648,"remaining_time":1.285908292},
{"learn":[0.3258255731],"iteration":254,"passed_time":0.4389457186,"remaining_time":1.282410041},
{"learn":[0.3252532715],"iteration":255,"passed_time":0.4401440446,"remaining_time":1.27916863},
{"learn":[0.3241788577],"iteration":256,"passed_time":0.4411776779,"remaining_time":1.275466983},
{"learn":[0.3236616593],"iteration":257,"passed_time":0.4423656225,"remaining_time":1.272229813},
{"learn":[0.3231503972],"iteration":258,"passed_time":0.443332066,"remaining_time":1.268374753},
{"learn":[0.3222751117],"iteration":259,"passed_time":0.4443261245,"remaining_time":1.264620508},
{"learn":[0.3218444631],"iteration":260,"passed_time":0.4453767025,"remaining_time":1.261047445},
{"learn":[0.321560683],"iteration":261,"passed_time":0.4461554986,"remaining_time":1.256728084},
{"learn":[0.320970867],"iteration":262,"passed_time":0.4471395858,"remaining_time":1.253010931},
{"learn":[0.3202918463],"iteration":263,"passed_time":0.4482625794,"remaining_time":1.249701737},
{"learn":[0.319548743],"iteration":264,"passed_time":0.4493270927,"remaining_time":1.246246842},
{"learn":[0.3188321862],"iteration":265,"passed_time":0.4503760548,"remaining_time":1.242767008},
{"learn":[0.3180678628],"iteration":266,"passed_time":0.4519161208,"remaining_time":1.24065362},
{"learn":[0.317747142],"iteration":267,"passed_time":0.4537772583,"remaining_time":1.239421467},
{"learn":[0.3169415774],"iteration":268,"passed_time":0.4552557413,"remaining_time":1.237144784},
{"learn":[0.3165389456],"iteration":269,"passed_time":0.4565913288,"remaining_time":1.234487667},
{"learn":[0.3159925083],"iteration":270,"passed_time":0.457735198,"remaining_time":1.231324573},
{"learn":[0.315503274],"iteration":271,"passed_time":0.4593091536,"remaining_time":1.229327441},
{"learn":[0.3148110931],"iteration":272,"passed_time":0.4609147381,"remaining_time":1.227417636},
{"learn":[0.3142846873],"iteration":273,"passed_time":0.4621954752,"remaining_time":1.224649325},
{"learn":[0.3135183321],"iteration":274,"passed_time":0.4638992461,"remaining_time":1.223007103},
{"learn":[0.3131274601],"iteration":275,"passed_time":0.4653279969,"remaining_time":1.220643006},
{"learn":[0.3127052284],"iteration":276,"passed_time":0.4669649182,"remaining_time":1.21882901},
{"learn":[0.3119375897],"iteration":277,"passed_time":0.4700715692,"remaining_time":1.220833356},
{"learn":[0.3111007494],"iteration":278,"passed_time":0.4715496838,"remaining_time":1.218592552},
{"learn":[0.3105615138],"iteration":279,"passed_time":0.4729314014,"remaining_time":1.216109318},
{"learn":[0.3099516265],"iteration":280,"passed_time":0.474123902,"remaining_time":1.213149771},
{"learn":[0.3091565307],"iteration":281,"passed_time":0.4754335284,"remaining_time":1.21050097},
{"learn":[0.3086144402],"iteration":282,"passed_time":0.476678246,"remaining_time":1.207697182},
{"learn":[0.3082581354],"iteration":283,"passed_time":0.4779437606,"remaining_time":1.204956805},
{"learn":[0.3076624007],"iteration":284,"passed_time":0.4792324202,"remaining_time":1.202284844},
{"learn":[0.3072877735],"iteration":285,"passed_time":0.480604603,"remaining_time":1.199831072},
{"learn":[0.3067226788],"iteration":286,"passed_time":0.4818526988,"remaining_time":1.197076565},
{"learn":[0.3061710948],"iteration":287,"passed_time":0.4829629082,"remaining_time":1.193991634},
{"learn":[0.3058593932],"iteration":288,"passed_time":0.4843929599,"remaining_time":1.191707247},
{"learn":[0.3052490804],"iteration":289,"passed_time":0.4858870012,"remaining_time":1.189585417},
{"learn":[0.3047985495],"iteration":290,"passed_time":0.4873158177,"remaining_time":1.187308985},
{"learn":[0.3045618904],"iteration":291,"passed_time":0.4885060567,"remaining_time":1.184459891},
{"learn":[0.3040432206],"iteration":292,"passed_time":0.4897850258,"remaining_time":1.181836223},
{"learn":[0.3035081632],"iteration":293,"passed_time":0.4910801243,"remaining_time":1.179260435},
{"learn":[0.3028518951],"iteration":294,"passed_time":0.4921979224,"remaining_time":1.176269611},
{"learn":[0.3024999615],"iteration":295,"passed_time":0.4934585748,"remaining_time":1.173631205},
{"learn":[0.3016202115],"iteration":296,"passed_time":0.494564846,"remaining_time":1.170636656},
{"learn":[0.3013151727],"iteration":297,"passed_time":0.4957015268,"remaining_time":1.167726415},
{"learn":[0.3005903837],"iteration":298,"passed_time":0.4968008962,"remaining_time":1.164740563},
{"learn":[0.3001569368],"iteration":299,"passed_time":0.4980693147,"remaining_time":1.162161734},
{"learn":[0.299337322],"iteration":300,"passed_time":0.5000652756,"remaining_time":1.161281155},
{"learn":[0.2987688051],"iteration":301,"passed_time":0.5015123767,"remaining_time":1.159124632},
{"learn":[0.2983723513],"iteration":302,"passed_time":0.5029531264,"remaining_time":1.156958182},
{"learn":[0.2980629136],"iteration":303,"passed_time":0.5042297754,"remaining_time":1.154420802},
{"learn":[0.2969707555],"iteration":304,"passed_time":0.5054999866,"remaining_time":1.151877019},
{"learn":[0.2965248064],"iteration":305,"passed_time":0.5067629078,"remaining_time":1.149325026},
{"learn":[0.2962360637],"iteration":306,"passed_time":0.508011773,"remaining_time":1.146749703},
{"learn":[0.2954590216],"iteration":307,"passed_time":0.5095012687,"remaining_time":1.14472363},
{"learn":[0.294714604],"iteration":308,"passed_time":0.5107858587,"remaining_time":1.14224281},
{"learn":[0.2945974165],"iteration":309,"passed_time":0.5119384469,"remaining_time":1.139475898},
{"learn":[0.2941458184],"iteration":310,"passed_time":0.5132273167,"remaining_time":1.13702129},
{"learn":[0.2938647201],"iteration":311,"passed_time":0.514470959,"remaining_time":1.134474422},
{"learn":[0.2932944639],"iteration":312,"passed_time":0.5156618493,"remaining_time":1.131820097},
{"learn":[0.2928941598],"iteration":313,"passed_time":0.5169188287,"remaining_time":1.129319479},
{"learn":[0.2923895538],"iteration":314,"passed_time":0.518093827,"remaining_time":1.126648481},
{"learn":[0.2916519207],"iteration":315,"passed_time":0.5194279474,"remaining_time":1.12433138},
{"learn":[0.2912552181],"iteration":316,"passed_time":0.5206705708,"remaining_time":1.121823343},
{"learn":[0.2906376756],"iteration":317,"passed_time":0.5219903816,"remaining_time":1.119488806},
{"learn":[0.2902440324],"iteration":318,"passed_time":0.5230224428,"remaining_time":1.116546343},
{"learn":[0.2894606608],"iteration":319,"passed_time":0.5239337283,"remaining_time":1.113359173},
{"learn":[0.2890371415],"iteration":320,"passed_time":0.5248703339,"remaining_time":1.110239741},
{"learn":[0.2883319589],"iteration":321,"passed_time":0.5258048874,"remaining_time":1.107129546},
{"learn":[0.287824222],"iteration":322,"passed_time":0.5267305785,"remaining_time":1.104014246},
{"learn":[0.2871587799],"iteration":323,"passed_time":0.5276663143,"remaining_time":1.100933421},
{"learn":[0.2865013334],"iteration":324,"passed_time":0.5286035848,"remaining_time":1.097868984},
{"learn":[0.286305289],"iteration":325,"passed_time":0.5294971671,"remaining_time":1.094727272},
{"learn":[0.2853172852],"iteration":326,"passed_time":0.531008717,"remaining_time":1.092871152},
{"learn":[0.2842556079],"iteration":327,"passed_time":0.5323756736,"remaining_time":1.090720892},
{"learn":[0.2838693448],"iteration":328,"passed_time":0.5334004972,"remaining_time":1.08787761},
{"learn":[0.2833058967],"iteration":329,"passed_time":0.534440681,"remaining_time":1.085076534},
{"learn":[0.2829675898],"iteration":330,"passed_time":0.5354730838,"remaining_time":1.082270372},
{"learn":[0.2823460633],"iteration":331,"passed_time":0.5365255779,"remaining_time":1.079515319},
{"learn":[0.2816063807],"iteration":332,"passed_time":0.5375441489,"remaining_time":1.076702545},
{"learn":[0.281390362],"iteration":333,"passed_time":0.5385675832,"remaining_time":1.073910211},
{"learn":[0.2809517764],"iteration":334,"passed_time":0.5395808802,"remaining_time":1.071108314},
{"learn":[0.279661283],"iteration":335,"passed_time":0.5406122797,"remaining_time":1.068352838},
{"learn":[0.2790391108],"iteration":336,"passed_time":0.5416313239,"remaining_time":1.065583287},
{"learn":[0.2783835139],"iteration":337,"passed_time":0.5427814274,"remaining_time":1.063080784},
{"learn":[0.2779060602],"iteration":338,"passed_time":0.5437100125,"remaining_time":1.060154331},
{"learn":[0.2773771908],"iteration":339,"passed_time":0.544611019,"remaining_time":1.057186096},
{"learn":[0.2767221632],"iteration":340,"passed_time":0.546064484,"remaining_time":1.055297639},
{"learn":[0.2763186839],"iteration":341,"passed_time":0.5470808052,"remaining_time":1.052570672},
{"learn":[0.27594446],"iteration":342,"passed_time":0.548163395,"remaining_time":1.049980614},
{"learn":[0.2752856121],"iteration":343,"passed_time":0.5491196563,"remaining_time":1.047158414},
{"learn":[0.274555361],"iteration":344,"passed_time":0.5500437368,"remaining_time":1.044285935},
{"learn":[0.274079533],"iteration":345,"passed_time":0.5509831503,"remaining_time":1.0414537},
{"learn":[0.2739491182],"iteration":346,"passed_time":0.5518949315,"remaining_time":1.038580375},
{"learn":[0.2736396785],"iteration":347,"passed_time":0.5528375349,"remaining_time":1.035776071},
{"learn":[0.2728477806],"iteration":348,"passed_time":0.5539142215,"remaining_time":1.033232545},
{"learn":[0.2723575909],"iteration":349,"passed_time":0.5548399371,"remaining_time":1.030417026},
{"learn":[0.2716403517],"iteration":350,"passed_time":0.555756972,"remaining_time":1.027596225},
{"learn":[0.2712778419],"iteration":351,"passed_time":0.5566800396,"remaining_time":1.024797346},
{"learn":[0.2707240138],"iteration":352,"passed_time":0.5576161812,"remaining_time":1.022033057},
{"learn":[0.2701988701],"iteration":353,"passed_time":0.5585425354,"remaining_time":1.019261237},
{"learn":[0.2695088978],"iteration":354,"passed_time":0.5594687407,"remaining_time":1.016499543},
{"learn":[0.2691353999],"iteration":355,"passed_time":0.5604777808,"remaining_time":1.013898008},
{"learn":[0.2688846434],"iteration":356,"passed_time":0.5617451037,"remaining_time":1.011770593},
{"learn":[0.2686519266],"iteration":357,"passed_time":0.5629655061,"remaining_time":1.009563841},
{"learn":[0.2680968868],"iteration":358,"passed_time":0.5640528182,"remaining_time":1.007124948},
{"learn":[0.2676839994],"iteration":359,"passed_time":0.5651843403,"remaining_time":1.00477216},
{"learn":[0.2675802777],"iteration":360,"passed_time":0.5663864817,"remaining_time":1.002551141},
{"learn":[0.2667411344],"iteration":361,"passed_time":0.5673330922,"remaining_time":0.9998853945},
{"learn":[0.2663397367],"iteration":362,"passed_time":0.5682716249,"remaining_time":0.9972149451},
{"learn":[0.2658082053],"iteration":363,"passed_time":0.5692135306,"remaining_time":0.9945599051},
{"learn":[0.2654400551],"iteration":364,"passed_time":0.5701485149,"remaining_time":0.9919022108},
{"learn":[0.2647734002],"iteration":365,"passed_time":0.5710741667,"remaining_time":0.9892377642},
{"learn":[0.2642056509],"iteration":366,"passed_time":0.5720062088,"remaining_time":0.9865938152},
{"learn":[0.2639186839],"iteration":367,"passed_time":0.5729316568,"remaining_time":0.9839478454},
{"learn":[0.263342749],"iteration":368,"passed_time":0.5738544575,"remaining_time":0.9813066739},
{"learn":[0.2628669123],"iteration":369,"passed_time":0.5747840792,"remaining_time":0.9786864052},
{"learn":[0.262464934],"iteration":370,"passed_time":0.5757115758,"remaining_time":0.9760716473},
{"learn":[0.2620413258],"iteration":371,"passed_time":0.5774973788,"remaining_time":0.9749149297},
{"learn":[0.2616528179],"iteration":372,"passed_time":0.5787696299,"remaining_time":0.9728915763},
{"learn":[0.2612748198],"iteration":373,"passed_time":0.5798925279,"remaining_time":0.9706222526},
{"learn":[0.2608678846],"iteration":374,"passed_time":0.5811596438,"remaining_time":0.9685994064},
{"learn":[0.2601861371],"iteration":375,"passed_time":0.5823645407,"remaining_time":0.9664773229},
{"learn":[0.259849636],"iteration":376,"passed_time":0.5837708894,"remaining_time":0.9646930081},
{"learn":[0.2594130853],"iteration":377,"passed_time":0.5851001266,"remaining_time":0.9627838061},
{"learn":[0.2591614358],"iteration":378,"passed_time":0.5863331469,"remaining_time":0.9607200112},
{"learn":[0.2588888],"iteration":379,"passed_time":0.587552155,"remaining_time":0.9586377266},
{"learn":[0.2586279418],"iteration":380,"passed_time":0.588752486,"remaining_time":0.9565296294},
{"learn":[0.2581880971],"iteration":381,"passed_time":0.5898577375,"remaining_time":0.9542724654},
{"learn":[0.2577876449],"iteration":382,"passed_time":0.5909994546,"remaining_time":0.9520800614},
{"learn":[0.2575406328],"iteration":383,"passed_time":0.5927669792,"remaining_time":0.9508970291},
{"learn":[0.2568663306],"iteration":384,"passed_time":0.5949019782,"remaining_time":0.9502979652},
{"learn":[0.2563960672],"iteration":385,"passed_time":0.5963055171,"remaining_time":0.9485274287},
{"learn":[0.2559345138],"iteration":386,"passed_time":0.5975292613,"remaining_time":0.9464739979},
{"learn":[0.2554632945],"iteration":387,"passed_time":0.5987269439,"remaining_time":0.9443837362},
{"learn":[0.2552159535],"iteration":388,"passed_time":0.5998466574,"remaining_time":0.9421755981},
{"learn":[0.2545312539],"iteration":389,"passed_time":0.6010767802,"remaining_time":0.9401457332},
{"learn":[0.2540632351],"iteration":390,"passed_time":0.6029447763,"remaining_time":0.9391134751},
{"learn":[0.2538057796],"iteration":391,"passed_time":0.6043550713,"remaining_time":0.9373670494},
{"learn":[0.2534936867],"iteration":392,"passed_time":0.6054827619,"remaining_time":0.9351858434},
{"learn":[0.2528923306],"iteration":393,"passed_time":0.6068425647,"remaining_time":0.9333669904},
{"learn":[0.2521437317],"iteration":394,"passed_time":0.6085015235,"remaining_time":0.9320086626},
{"learn":[0.2516071085],"iteration":395,"passed_time":0.6097100103,"remaining_time":0.929961733},
{"learn":[0.2514384859],"iteration":396,"passed_time":0.6112171225,"remaining_time":0.9283726067},
{"learn":[0.251010711],"iteration":397,"passed_time":0.6124921034,"remaining_time":0.9264327795},
{"learn":[0.2505214454],"iteration":398,"passed_time":0.6136867731,"remaining_time":0.9243753149},
{"learn":[0.2499344906],"iteration":399,"passed_time":0.614951979,"remaining_time":0.9224279685},
{"learn":[0.2492745023],"iteration":400,"passed_time":0.616059899,"remaining_time":0.920249076},
{"learn":[0.2487390067],"iteration":401,"passed_time":0.6173599952,"remaining_time":0.9183613859},
{"learn":[0.2482641492],"iteration":402,"passed_time":0.6184901551,"remaining_time":0.9162248699},
{"learn":[0.2473634112],"iteration":403,"passed_time":0.6199710737,"remaining_time":0.9146107919},
{"learn":[0.2467967237],"iteration":404,"passed_time":0.6212370394,"remaining_time":0.9126815765},
{"learn":[0.2465738047],"iteration":405,"passed_time":0.6225164425,"remaining_time":0.9107752878},
{"learn":[0.2460965636],"iteration":406,"passed_time":0.624000232,"remaining_time":0.9091698711},
{"learn":[0.2454578831],"iteration":407,"passed_time":0.62515146,"remaining_time":0.9070825106},
{"learn":[0.2448186576],"iteration":408,"passed_time":0.626305671,"remaining_time":0.905004038},
{"learn":[0.2445725427],"iteration":409,"passed_time":0.6273079681,"remaining_time":0.9027114663},
{"learn":[0.2443573479],"iteration":410,"passed_time":0.6287160372,"remaining_time":0.9010066811},
{"learn":[0.2438872659],"iteration":411,"passed_time":0.6297782169,"remaining_time":0.8988096881},
{"learn":[0.243347858],"iteration":412,"passed_time":0.6310759488,"remaining_time":0.8969529829},
{"learn":[0.2428444676],"iteration":413,"passed_time":0.6321821839,"remaining_time":0.8948279221},
{"learn":[0.2427120104],"iteration":414,"passed_time":0.6334833882,"remaining_time":0.8929826075},
{"learn":[0.2422235636],"iteration":415,"passed_time":0.6345971689,"remaining_time":0.8908767948},
{"learn":[0.2416713636],"iteration":416,"passed_time":0.6356249814,"remaining_time":0.8886555495},
{"learn":[0.2408248232],"iteration":417,"passed_time":0.6367244675,"remaining_time":0.8865398088},
{"learn":[0.2402806848],"iteration":418,"passed_time":0.6380832018,"remaining_time":0.8847884015},
{"learn":[0.240057416],"iteration":419,"passed_time":0.6394737676,"remaining_time":0.8830828219},
{"learn":[0.2396274279],"iteration":420,"passed_time":0.6407531742,"remaining_time":0.881225862},
{"learn":[0.2393320801],"iteration":421,"passed_time":0.6423937497,"remaining_time":0.8798663206},
{"learn":[0.2388880488],"iteration":422,"passed_time":0.643734719,"remaining_time":0.878096768},
{"learn":[0.2382237759],"iteration":423,"passed_time":0.6448365523,"remaining_time":0.876004373},
{"learn":[0.2374501807],"iteration":424,"passed_time":0.6459462678,"remaining_time":0.8739273034},
{"learn":[0.2365895033],"iteration":425,"passed_time":0.6473270896,"remaining_time":0.8722200691},
{"learn":[0.2361074851],"iteration":426,"passed_time":0.6486978141,"remaining_time":0.8705008138},
{"learn":[0.2355635736],"iteration":427,"passed_time":0.6501214915,"remaining_time":0.868853956},
{"learn":[0.2353565336],"iteration":428,"passed_time":0.6516446741,"remaining_time":0.8673405802},
{"learn":[0.2350213804],"iteration":429,"passed_time":0.6529463067,"remaining_time":0.8655334764},
{"learn":[0.234718589],"iteration":430,"passed_time":0.6550737434,"remaining_time":0.8648189327},
{"learn":[0.2344797175],"iteration":431,"passed_time":0.6565238627,"remaining_time":0.863207301},
{"learn":[0.2339951111],"iteration":432,"passed_time":0.6577882442,"remaining_time":0.8613531974},
{"learn":[0.2336512808],"iteration":433,"passed_time":0.6590229748,"remaining_time":0.8594631422},
{"learn":[0.2331383207],"iteration":434,"passed_time":0.6602917196,"remaining_time":0.8576202794},
{"learn":[0.2326828141],"iteration":435,"passed_time":0.661297734,"remaining_time":0.855440188},
{"learn":[0.2320773203],"iteration":436,"passed_time":0.6622727698,"remaining_time":0.8532255593},
{"learn":[0.2317152856],"iteration":437,"passed_time":0.6632836075,"remaining_time":0.8510625284},
{"learn":[0.2314373957],"iteration":438,"passed_time":0.6642746018,"remaining_time":0.8488793886},
{"learn":[0.2311224359],"iteration":439,"passed_time":0.6652646989,"remaining_time":0.8467005258},
{"learn":[0.230603354],"iteration":440,"passed_time":0.6662957237,"remaining_time":0.8445789332},
{"learn":[0.2304072054],"iteration":441,"passed_time":0.6671970788,"remaining_time":0.8422985746},
{"learn":[0.230098993],"iteration":442,"passed_time":0.6682145963,"remaining_time":0.8401704969},
{"learn":[0.2297568702],"iteration":443,"passed_time":0.6698490344,"remaining_time":0.838819962},
{"learn":[0.229416591],"iteration":444,"passed_time":0.6713326472,"remaining_time":0.8372800431},
{"learn":[0.2290431013],"iteration":445,"passed_time":0.6726127605,"remaining_time":0.8354875993},
{"learn":[0.2284687011],"iteration":446,"passed_time":0.6736257502,"remaining_time":0.8333669795},
{"learn":[0.2280747066],"iteration":447,"passed_time":0.6746530955,"remaining_time":0.8312689926},
{"learn":[0.2279712603],"iteration":448,"passed_time":0.6756559765,"remaining_time":0.8291457528},
{"learn":[0.2273371737],"iteration":449,"passed_time":0.6766642118,"remaining_time":0.8270340366},
{"learn":[0.2269929084],"iteration":450,"passed_time":0.6776562945,"remaining_time":0.8249075514},
{"learn":[0.2264080174],"iteration":451,"passed_time":0.6786542152,"remaining_time":0.8227931635},
{"learn":[0.2261457931],"iteration":452,"passed_time":0.6796647845,"remaining_time":0.8206989782},
{"learn":[0.2257222749],"iteration":453,"passed_time":0.6806794722,"remaining_time":0.8186145195},
{"learn":[0.2254093022],"iteration":454,"passed_time":0.6817006888,"remaining_time":0.8165425833},
{"learn":[0.2248155412],"iteration":455,"passed_time":0.6828022412,"remaining_time":0.8145710948},
{"learn":[0.2242316697],"iteration":456,"passed_time":0.6838950322,"remaining_time":0.8125930032},
{"learn":[0.2238596469],"iteration":457,"passed_time":0.6853150459,"remaining_time":0.811006015},
{"learn":[0.223348273],"iteration":458,"passed_time":0.6865569048,"remaining_time":0.8092097724},
{"learn":[0.2232251417],"iteration":459,"passed_time":0.687697895,"remaining_time":0.8072975289},
{"learn":[0.2228035133],"iteration":460,"passed_time":0.6887388697,"remaining_time":0.8052716936},
{"learn":[0.222531067],"iteration":461,"passed_time":0.6897605734,"remaining_time":0.8032276807},
{"learn":[0.2220695748],"iteration":462,"passed_time":0.6907776059,"remaining_time":0.801182666},
{"learn":[0.2217611379],"iteration":463,"passed_time":0.6919442831,"remaining_time":0.7993149477},
{"learn":[0.2214515614],"iteration":464,"passed_time":0.6928713389,"remaining_time":0.7971745512},
{"learn":[0.2213441331],"iteration":465,"passed_time":0.6937936242,"remaining_time":0.7950338955},
{"learn":[0.2206919985],"iteration":466,"passed_time":0.6947200083,"remaining_time":0.7929031358},
{"learn":[0.2204602589],"iteration":467,"passed_time":0.6956463353,"remaining_time":0.7907774581},
{"learn":[0.2200392263],"iteration":468,"passed_time":0.6965670949,"remaining_time":0.7886505915},
{"learn":[0.2194718355],"iteration":469,"passed_time":0.6974792473,"remaining_time":0.7865191512},
{"learn":[0.2192527932],"iteration":470,"passed_time":0.6984014376,"remaining_time":0.7844041624},
{"learn":[0.2189004972],"iteration":471,"passed_time":0.6993533064,"remaining_time":0.7823274275},
{"learn":[0.2186321344],"iteration":472,"passed_time":0.7012014459,"remaining_time":0.7812540422},
{"learn":[0.2182464317],"iteration":473,"passed_time":0.7022976668,"remaining_time":0.7793429805},
{"learn":[0.2180282856],"iteration":474,"passed_time":0.7033325321,"remaining_time":0.7773675354},
{"learn":[0.2176384175],"iteration":475,"passed_time":0.7043504392,"remaining_time":0.7753773743},
{"learn":[0.2174437786],"iteration":476,"passed_time":0.7053694688,"remaining_time":0.7733925203},
{"learn":[0.2171388612],"iteration":477,"passed_time":0.7063477227,"remaining_time":0.7713671784},
{"learn":[0.2167063695],"iteration":478,"passed_time":0.707340465,"remaining_time":0.7693619672},
{"learn":[0.2162629436],"iteration":479,"passed_time":0.708353101,"remaining_time":0.7673825261},
{"learn":[0.2159176399],"iteration":480,"passed_time":0.7093493836,"remaining_time":0.7653894596},
{"learn":[0.2158245235],"iteration":481,"passed_time":0.7103249519,"remaining_time":0.7633782679},
{"learn":[0.2155269987],"iteration":482,"passed_time":0.7113518537,"remaining_time":0.7614263113},
{"learn":[0.2151824158],"iteration":483,"passed_time":0.7125720459,"remaining_time":0.7596842473},
{"learn":[0.2150068949],"iteration":484,"passed_time":0.7138096272,"remaining_time":0.7579628001},
{"learn":[0.2147103866],"iteration":485,"passed_time":0.7153585618,"remaining_time":0.7565726353},
{"learn":[0.2144561092],"iteration":486,"passed_time":0.7163968988,"remaining_time":0.7546439611},
{"learn":[0.2140561033],"iteration":487,"passed_time":0.7174162881,"remaining_time":0.7526990564},
{"learn":[0.2137189647],"iteration":488,"passed_time":0.7183892758,"remaining_time":0.7507094477},
{"learn":[0.2129698026],"iteration":489,"passed_time":0.7193793047,"remaining_time":0.7487417253},
{"learn":[0.21239831],"iteration":490,"passed_time":0.7203922869,"remaining_time":0.7468017801},
{"learn":[0.2122051675],"iteration":491,"passed_time":0.7213949802,"remaining_time":0.7448549795},
{"learn":[0.2118248056],"iteration":492,"passed_time":0.7223831897,"remaining_time":0.7428971139},
{"learn":[0.2114924819],"iteration":493,"passed_time":0.7233798245,"remaining_time":0.740951804},
{"learn":[0.2113181403],"iteration":494,"passed_time":0.7243886151,"remaining_time":0.7390227285},
{"learn":[0.2111725463],"iteration":495,"passed_time":0.7253790437,"remaining_time":0.7370787057},
{"learn":[0.2106562492],"iteration":496,"passed_time":0.7263820021,"remaining_time":0.7351512014},
{"learn":[0.2104472594],"iteration":497,"passed_time":0.7274736157,"remaining_time":0.7333167773},
{"learn":[0.2100386865],"iteration":498,"passed_time":0.729235535,"remaining_time":0.7321583227},
{"learn":[0.2097938607],"iteration":499,"passed_time":0.7307283889,"remaining_time":0.7307283889},
{"learn":[0.2094338989],"iteration":500,"passed_time":0.732272931,"remaining_time":0.7293496857},
{"learn":[0.2092874872],"iteration":501,"passed_time":0.7337045237,"remaining_time":0.7278582725},
{"learn":[0.2087656997],"iteration":502,"passed_time":0.7351284596,"remaining_time":0.7263595316},
{"learn":[0.2084570273],"iteration":503,"passed_time":0.7366875018,"remaining_time":0.7249940494},
{"learn":[0.208061347],"iteration":504,"passed_time":0.737989068,"remaining_time":0.7233754231},
{"learn":[0.2076730917],"iteration":505,"passed_time":0.7397263627,"remaining_time":0.722183445},
{"learn":[0.2074658718],"iteration":506,"passed_time":0.7406791416,"remaining_time":0.7202264631},
{"learn":[0.2071965026],"iteration":507,"passed_time":0.7415896661,"remaining_time":0.7182325113},
{"learn":[0.2067691812],"iteration":508,"passed_time":0.7425088548,"remaining_time":0.7162511743},
{"learn":[0.2063300392],"iteration":509,"passed_time":0.7438356627,"remaining_time":0.7146656367},
{"learn":[0.2060369832],"iteration":510,"passed_time":0.744876035,"remaining_time":0.712807008},
{"learn":[0.2055191006],"iteration":511,"passed_time":0.7461302952,"remaining_time":0.7111554377},
{"learn":[0.2053164183],"iteration":512,"passed_time":0.7471073147,"remaining_time":0.7092422266},
{"learn":[0.2050179737],"iteration":513,"passed_time":0.7480492175,"remaining_time":0.7072994547},
{"learn":[0.2048933782],"iteration":514,"passed_time":0.7489551444,"remaining_time":0.7053266893},
{"learn":[0.2047544994],"iteration":515,"passed_time":0.7498964515,"remaining_time":0.7033912452},
{"learn":[0.2042875601],"iteration":516,"passed_time":0.7508393851,"remaining_time":0.7014611663},
{"learn":[0.2041500111],"iteration":517,"passed_time":0.7517482462,"remaining_time":0.6995031943},
{"learn":[0.2039588883],"iteration":518,"passed_time":0.7526626073,"remaining_time":0.6975543624},
{"learn":[0.2037895598],"iteration":519,"passed_time":0.753603337,"remaining_time":0.6956338496},
{"learn":[0.2031392679],"iteration":520,"passed_time":0.7545407271,"remaining_time":0.6937140274},
{"learn":[0.20300861],"iteration":521,"passed_time":0.7554462606,"remaining_time":0.691768798},
{"learn":[0.2028260394],"iteration":522,"passed_time":0.7563738339,"remaining_time":0.6898476458},
{"learn":[0.2025560895],"iteration":523,"passed_time":0.7573038475,"remaining_time":0.6879325027},
{"learn":[0.202300693],"iteration":524,"passed_time":0.7583766776,"remaining_time":0.6861503273},
{"learn":[0.2020048654],"iteration":525,"passed_time":0.7597695931,"remaining_time":0.6846592911},
{"learn":[0.2017727525],"iteration":526,"passed_time":0.7609681935,"remaining_time":0.682994223},
{"learn":[0.2014940394],"iteration":527,"passed_time":0.7622973569,"remaining_time":0.6814476372},
{"learn":[0.2010086894],"iteration":528,"passed_time":0.763544633,"remaining_time":0.6798289643},
{"learn":[0.2006942736],"iteration":529,"passed_time":0.7648094456,"remaining_time":0.6782272442},
{"learn":[0.200265567],"iteration":530,"passed_time":0.7659851359,"remaining_time":0.6765480767},
{"learn":[0.199724964],"iteration":531,"passed_time":0.7669982148,"remaining_time":0.6747277529},
{"learn":[0.1994344562],"iteration":532,"passed_time":0.7679375509,"remaining_time":0.6728458467},
{"learn":[0.1992022197],"iteration":533,"passed_time":0.7690311638,"remaining_time":0.6711021017},
{"learn":[0.1989173019],"iteration":534,"passed_time":0.7699904026,"remaining_time":0.6692439947},
{"learn":[0.1986757937],"iteration":535,"passed_time":0.7709251324,"remaining_time":0.667368025},
{"learn":[0.1983352821],"iteration":536,"passed_time":0.7718370559,"remaining_time":0.6654758974},
{"learn":[0.1981760005],"iteration":537,"passed_time":0.7727668465,"remaining_time":0.6636027567},
{"learn":[0.1980076728],"iteration":538,"passed_time":0.7737064888,"remaining_time":0.6617415424},
{"learn":[0.1976402609],"iteration":539,"passed_time":0.7748073743,"remaining_time":0.6600210966},
{"learn":[0.1974168337],"iteration":540,"passed_time":0.7758755959,"remaining_time":0.6582752283},
{"learn":[0.1971686591],"iteration":541,"passed_time":0.7772210278,"remaining_time":0.6567661083},
{"learn":[0.1970650991],"iteration":542,"passed_time":0.7781449676,"remaining_time":0.6549028549},
{"learn":[0.1966526837],"iteration":543,"passed_time":0.7790808933,"remaining_time":0.6530531018},
{"learn":[0.1963015162],"iteration":544,"passed_time":0.7800151792,"remaining_time":0.6512053331},
{"learn":[0.1961471247],"iteration":545,"passed_time":0.7809342001,"remaining_time":0.6493482177},
{"learn":[0.1957523953],"iteration":546,"passed_time":0.781866804,"remaining_time":0.647505781},
{"learn":[0.1954023245],"iteration":547,"passed_time":0.7827874319,"remaining_time":0.6456567869},
{"learn":[0.1952675095],"iteration":548,"passed_time":0.7837032091,"remaining_time":0.64380719},
{"learn":[0.1949069552],"iteration":549,"passed_time":0.7846362969,"remaining_time":0.641975152},
{"learn":[0.1946947738],"iteration":550,"passed_time":0.7855475727,"remaining_time":0.6401286028},
{"learn":[0.1944106266],"iteration":551,"passed_time":0.7864598824,"remaining_time":0.6382862814},
{"learn":[0.1942606381],"iteration":552,"passed_time":0.787395436,"remaining_time":0.6364661119},
{"learn":[0.1935735819],"iteration":553,"passed_time":0.7883049884,"remaining_time":0.6346282036},
{"learn":[0.1931984178],"iteration":554,"passed_time":0.7897791905,"remaining_time":0.633246378},
{"learn":[0.1930272317],"iteration":555,"passed_time":0.7912601067,"remaining_time":0.6318695816},
{"learn":[0.192741312],"iteration":556,"passed_time":0.7924056343,"remaining_time":0.630225666},
{"learn":[0.1923150519],"iteration":557,"passed_time":0.793381905,"remaining_time":0.6284494659},
{"learn":[0.1921320559],"iteration":558,"passed_time":0.7943233492,"remaining_time":0.6266486529},
{"learn":[0.1920645284],"iteration":559,"passed_time":0.795255402,"remaining_time":0.6248435302},
{"learn":[0.1918841197],"iteration":560,"passed_time":0.7961639398,"remaining_time":0.6230231187},
{"learn":[0.1914177808],"iteration":561,"passed_time":0.7970995979,"remaining_time":0.6212270888},
{"learn":[0.1911188545],"iteration":562,"passed_time":0.7980478786,"remaining_time":0.6194439129},
{"learn":[0.1909423934],"iteration":563,"passed_time":0.7989795753,"remaining_time":0.6176508774},
{"learn":[0.1906113087],"iteration":564,"passed_time":0.7999235198,"remaining_time":0.6158703206},
{"learn":[0.19013705],"iteration":565,"passed_time":0.8008602047,"remaining_time":0.6140871534},
{"learn":[0.189704453],"iteration":566,"passed_time":0.8017743466,"remaining_time":0.6122897568},
{"learn":[0.1895580055],"iteration":567,"passed_time":0.802704654,"remaining_time":0.610507765},
{"learn":[0.1893053257],"iteration":568,"passed_time":0.8036195664,"remaining_time":0.6087171057},
{"learn":[0.1888827622],"iteration":569,"passed_time":0.8045285107,"remaining_time":0.6069250169},
{"learn":[0.188702768],"iteration":570,"passed_time":0.8060047367,"remaining_time":0.6055622278},
{"learn":[0.1882245838],"iteration":571,"passed_time":0.8072305945,"remaining_time":0.6040117035},
{"learn":[0.1878339878],"iteration":572,"passed_time":0.8082563774,"remaining_time":0.6023132166},
{"learn":[0.1874535854],"iteration":573,"passed_time":0.8091885248,"remaining_time":0.6005475811},
{"learn":[0.1869981035],"iteration":574,"passed_time":0.8101195195,"remaining_time":0.5987839926},
{"learn":[0.1867391987],"iteration":575,"passed_time":0.811047314,"remaining_time":0.5970209395},
{"learn":[0.1864640892],"iteration":576,"passed_time":0.8119929498,"remaining_time":0.595273861},
{"learn":[0.1863765309],"iteration":577,"passed_time":0.8128991675,"remaining_time":0.5935007763},
{"learn":[0.1860735466],"iteration":578,"passed_time":0.8138336896,"remaining_time":0.5917512666},
{"learn":[0.1859504545],"iteration":579,"passed_time":0.8147789589,"remaining_time":0.5900123496},
{"learn":[0.1858165221],"iteration":580,"passed_time":0.8156901648,"remaining_time":0.5882515991},
{"learn":[0.1857267196],"iteration":581,"passed_time":0.8167177239,"remaining_time":0.5865773344},
{"learn":[0.1856063087],"iteration":582,"passed_time":0.8177301865,"remaining_time":0.5848944902},
{"learn":[0.1853331337],"iteration":583,"passed_time":0.8187616774,"remaining_time":0.5832274962},
{"learn":[0.1851259081],"iteration":584,"passed_time":0.8199309962,"remaining_time":0.5816604503},
{"learn":[0.184962623],"iteration":585,"passed_time":0.8213461035,"remaining_time":0.5802684076},
{"learn":[0.1843750985],"iteration":586,"passed_time":0.8226873716,"remaining_time":0.5788243347},
{"learn":[0.1840693179],"iteration":587,"passed_time":0.8237940285,"remaining_time":0.5772162241},
{"learn":[0.18369698],"iteration":588,"passed_time":0.8248330247,"remaining_time":0.5755626029},
{"learn":[0.1834614414],"iteration":589,"passed_time":0.8259876835,"remaining_time":0.573991441},
{"learn":[0.1832139861],"iteration":590,"passed_time":0.8269254939,"remaining_time":0.5722716193},
{"learn":[0.1830109038],"iteration":591,"passed_time":0.8278412718,"remaining_time":0.5705392549},
{"learn":[0.182858491],"iteration":592,"passed_time":0.8287761087,"remaining_time":0.5688227255},
{"learn":[0.1825266016],"iteration":593,"passed_time":0.8297097051,"remaining_time":0.5671079802},
{"learn":[0.1823099852],"iteration":594,"passed_time":0.8306253991,"remaining_time":0.565383675},
{"learn":[0.1821149597],"iteration":595,"passed_time":0.8315396131,"remaining_time":0.56366108},
{"learn":[0.1819645449],"iteration":596,"passed_time":0.8324566912,"remaining_time":0.5619431265},
{"learn":[0.1812366637],"iteration":597,"passed_time":0.8333888322,"remaining_time":0.5602379775},
{"learn":[0.1808690034],"iteration":598,"passed_time":0.8343219321,"remaining_time":0.5585360514},
{"learn":[0.1806481548],"iteration":599,"passed_time":0.8355077475,"remaining_time":0.557005165},
{"learn":[0.1803668403],"iteration":600,"passed_time":0.8367862477,"remaining_time":0.5555369598},
{"learn":[0.1801537746],"iteration":601,"passed_time":0.8380642482,"remaining_time":0.5540690545},
{"learn":[0.1799770038],"iteration":602,"passed_time":0.8390611582,"remaining_time":0.5524167161},
{"learn":[0.1797095043],"iteration":603,"passed_time":0.8399941447,"remaining_time":0.5507246379},
{"learn":[0.1792606584],"iteration":604,"passed_time":0.8409114871,"remaining_time":0.5490248552},
{"learn":[0.1790128819],"iteration":605,"passed_time":0.841834837,"remaining_time":0.5473315607},
{"learn":[0.1785778113],"iteration":606,"passed_time":0.8427832105,"remaining_time":0.5456570045},
{"learn":[0.178510877],"iteration":607,"passed_time":0.8436913718,"remaining_time":0.5439589108},
{"learn":[0.1780258216],"iteration":608,"passed_time":0.8445981291,"remaining_time":0.5422625098},
{"learn":[0.1778942241],"iteration":609,"passed_time":0.8455315685,"remaining_time":0.5405857569},
{"learn":[0.177565817],"iteration":610,"passed_time":0.8464527467,"remaining_time":0.5389036309},
{"learn":[0.1769192075],"iteration":611,"passed_time":0.8473800826,"remaining_time":0.5372278955},
{"learn":[0.1767975766],"iteration":612,"passed_time":0.8483441012,"remaining_time":0.5355777604},
{"learn":[0.1765092615],"iteration":613,"passed_time":0.8493379062,"remaining_time":0.533948586},
{"learn":[0.1762961176],"iteration":614,"passed_time":0.8502961061,"remaining_time":0.5322991884},
{"learn":[0.1761023121],"iteration":615,"passed_time":0.8518889673,"remaining_time":0.5310476679},
{"learn":[0.17579593],"iteration":616,"passed_time":0.853087198,"remaining_time":0.5295500759},
{"learn":[0.1756931022],"iteration":617,"passed_time":0.8541148239,"remaining_time":0.5279479979},
{"learn":[0.1753958307],"iteration":618,"passed_time":0.8550542481,"remaining_time":0.5262934871},
{"learn":[0.1749951496],"iteration":619,"passed_time":0.8560005328,"remaining_time":0.5246454878},
{"learn":[0.1748388022],"iteration":620,"passed_time":0.8570110593,"remaining_time":0.5230389556},
{"learn":[0.1745947939],"iteration":621,"passed_time":0.8579683934,"remaining_time":0.521402014},
{"learn":[0.1743376082],"iteration":622,"passed_time":0.8589166351,"remaining_time":0.5197617519},
{"learn":[0.1742422154],"iteration":623,"passed_time":0.8599035363,"remaining_time":0.5181470027},
{"learn":[0.1740318448],"iteration":624,"passed_time":0.8608626748,"remaining_time":0.5165176049},
{"learn":[0.1737265236],"iteration":625,"passed_time":0.8618312104,"remaining_time":0.5148959628},
{"learn":[0.1732939502],"iteration":626,"passed_time":0.8627994227,"remaining_time":0.5132762116},
{"learn":[0.1730665551],"iteration":627,"passed_time":0.8637476252,"remaining_time":0.5116466825},
{"learn":[0.1729372936],"iteration":628,"passed_time":0.8646838604,"remaining_time":0.5100122611},
{"learn":[0.1728319285],"iteration":629,"passed_time":0.8656324348,"remaining_time":0.508387303},
{"learn":[0.1723923918],"iteration":630,"passed_time":0.8673579566,"remaining_time":0.5072188368},
{"learn":[0.1720044134],"iteration":631,"passed_time":0.8690148355,"remaining_time":0.5060086384},
{"learn":[0.1718485964],"iteration":632,"passed_time":0.8703716066,"remaining_time":0.5046230326},
{"learn":[0.1713188742],"iteration":633,"passed_time":0.871705842,"remaining_time":0.5032245082},
{"learn":[0.1711504435],"iteration":634,"passed_time":0.8731177291,"remaining_time":0.5018708206},
{"learn":[0.1709670469],"iteration":635,"passed_time":0.8746112968,"remaining_time":0.5005636981},
{"learn":[0.1706860766],"iteration":636,"passed_time":0.8760661872,"remaining_time":0.4992339497},
{"learn":[0.1702366306],"iteration":637,"passed_time":0.8777761811,"remaining_time":0.4980485541},
{"learn":[0.1697731251],"iteration":638,"passed_time":0.8790460261,"remaining_time":0.4966128567},
{"learn":[0.1695976231],"iteration":639,"passed_time":0.8800078866,"remaining_time":0.4950044362},
{"learn":[0.1694420967],"iteration":640,"passed_time":0.8809745492,"remaining_time":0.4934007226},
{"learn":[0.1692709998],"iteration":641,"passed_time":0.8828119772,"remaining_time":0.4922845605},
{"learn":[0.1689795595],"iteration":642,"passed_time":0.8847825972,"remaining_time":0.4912401045},
{"learn":[0.1688295807],"iteration":643,"passed_time":0.8859022475,"remaining_time":0.4897223604},
{"learn":[0.1686317089],"iteration":644,"passed_time":0.8868740072,"remaining_time":0.4881244536},
{"learn":[0.1682438882],"iteration":645,"passed_time":0.8878462526,"remaining_time":0.4865287514},
{"learn":[0.1680632206],"iteration":646,"passed_time":0.888803258,"remaining_time":0.4849266617},
{"learn":[0.1680137548],"iteration":647,"passed_time":0.8897554809,"remaining_time":0.4833239649},
{"learn":[0.1677966598],"iteration":648,"passed_time":0.8906963366,"remaining_time":0.481717125},
{"learn":[0.16732069],"iteration":649,"passed_time":0.8916322791,"remaining_time":0.4801096888},
{"learn":[0.1668817306],"iteration":650,"passed_time":0.8926033896,"remaining_time":0.4785231689},
{"learn":[0.1667155645],"iteration":651,"passed_time":0.8935612548,"remaining_time":0.4769314673},
{"learn":[0.1664656768],"iteration":652,"passed_time":0.8945181028,"remaining_time":0.4753411664},
{"learn":[0.1662851436],"iteration":653,"passed_time":0.8954739558,"remaining_time":0.4737522763},
{"learn":[0.1660681868],"iteration":654,"passed_time":0.8964074087,"remaining_time":0.4721535206},
{"learn":[0.165876602],"iteration":655,"passed_time":0.8977020579,"remaining_time":0.4707462011},
{"learn":[0.1657022076],"iteration":656,"passed_time":0.8989661153,"remaining_time":0.4693232535},
{"learn":[0.1656360957],"iteration":657,"passed_time":0.9001217766,"remaining_time":0.4678444493},
{"learn":[0.1651989661],"iteration":658,"passed_time":0.9014830188,"remaining_time":0.4664730036},
{"learn":[0.164817324],"iteration":659,"passed_time":0.9024529694,"remaining_time":0.4649000145},
{"learn":[0.1643919092],"iteration":660,"passed_time":0.9034279032,"remaining_time":0.4633314057},
{"learn":[0.1640406123],"iteration":661,"passed_time":0.9043903186,"remaining_time":0.4617581989},
{"learn":[0.1638231894],"iteration":662,"passed_time":0.9053668184,"remaining_time":0.4601939937},
{"learn":[0.1635301376],"iteration":663,"passed_time":0.906313926,"remaining_time":0.4586166855},
{"learn":[0.163481122],"iteration":664,"passed_time":0.9072589955,"remaining_time":0.4570402459},
{"learn":[0.1634256035],"iteration":665,"passed_time":0.9082134014,"remaining_time":0.4554703845},
{"learn":[0.1631760087],"iteration":666,"passed_time":0.9091926138,"remaining_time":0.4539147532},
{"learn":[0.162864828],"iteration":667,"passed_time":0.9101794818,"remaining_time":0.4523646526},
{"learn":[0.162618469],"iteration":668,"passed_time":0.9111481006,"remaining_time":0.4508072067},
{"learn":[0.1624826378],"iteration":669,"passed_time":0.912086775,"remaining_time":0.4492367698},
{"learn":[0.1622704227],"iteration":670,"passed_time":0.9136157395,"remaining_time":0.4479576428},
{"learn":[0.1617429542],"iteration":671,"passed_time":0.9146817574,"remaining_time":0.4464518102},
{"learn":[0.1614184426],"iteration":672,"passed_time":0.9158327257,"remaining_time":0.4449885606},
{"learn":[0.1612600877],"iteration":673,"passed_time":0.9168070328,"remaining_time":0.4434407903},
{"learn":[0.1610093862],"iteration":674,"passed_time":0.9177563481,"remaining_time":0.4418826861},
{"learn":[0.1607681077],"iteration":675,"passed_time":0.9187162054,"remaining_time":0.4403314357},
{"learn":[0.1605701911],"iteration":676,"passed_time":0.9196802885,"remaining_time":0.4387839486},
{"learn":[0.1599925766],"iteration":677,"passed_time":0.9206297401,"remaining_time":0.4372312335},
{"learn":[0.1598559882],"iteration":678,"passed_time":0.9215799026,"remaining_time":0.4356806314},
{"learn":[0.159643125],"iteration":679,"passed_time":0.9225544118,"remaining_time":0.4341432526},
{"learn":[0.1593578715],"iteration":680,"passed_time":0.9234868822,"remaining_time":0.4325878347},
{"learn":[0.1590886156],"iteration":681,"passed_time":0.924444551,"remaining_time":0.431045993},
{"learn":[0.1588633218],"iteration":682,"passed_time":0.9254122697,"remaining_time":0.4295105264},
{"learn":[0.1585981991],"iteration":683,"passed_time":0.9263823874,"remaining_time":0.4279778281},
{"learn":[0.1583257729],"iteration":684,"passed_time":0.9273180348,"remaining_time":0.4264309211},
{"learn":[0.1582240711],"iteration":685,"passed_time":0.9285836175,"remaining_time":0.4250368162},
{"learn":[0.1580803991],"iteration":686,"passed_time":0.9299438415,"remaining_time":0.4236862043},
{"learn":[0.1576285443],"iteration":687,"passed_time":0.9311760674,"remaining_time":0.422277519},
{"learn":[0.1573349165],"iteration":688,"passed_time":0.93217534,"remaining_time":0.4207641955},
{"learn":[0.1570629281],"iteration":689,"passed_time":0.9331395766,"remaining_time":0.4192366214},
{"learn":[0.1567940131],"iteration":690,"passed_time":0.934120496,"remaining_time":0.4177181379},
{"learn":[0.1564558114],"iteration":691,"passed_time":0.9350796281,"remaining_time":0.4161915108},
{"learn":[0.1559250404],"iteration":692,"passed_time":0.9360518653,"remaining_time":0.414672327},
{"learn":[0.1556455827],"iteration":693,"passed_time":0.9370093967,"remaining_time":0.4131482355},
{"learn":[0.1555398355],"iteration":694,"passed_time":0.9379779513,"remaining_time":0.4116306117},
{"learn":[0.1551395494],"iteration":695,"passed_time":0.93892542,"remaining_time":0.4101053559},
{"learn":[0.1550789961],"iteration":696,"passed_time":0.9398580353,"remaining_time":0.4085753009},
{"learn":[0.1546439996],"iteration":697,"passed_time":0.9408327136,"remaining_time":0.4070651569},
{"learn":[0.1545087378],"iteration":698,"passed_time":0.9418240394,"remaining_time":0.4055637137},
{"learn":[0.1543689335],"iteration":699,"passed_time":0.9427648812,"remaining_time":0.404042092},
{"learn":[0.1541609057],"iteration":700,"passed_time":0.9440689774,"remaining_time":0.4026770674},
{"learn":[0.1539055176],"iteration":701,"passed_time":0.9457253845,"remaining_time":0.4014617729},
{"learn":[0.1535834582],"iteration":702,"passed_time":0.9471086664,"remaining_time":0.4001298349},
{"learn":[0.153322326],"iteration":703,"passed_time":0.9483306905,"remaining_time":0.3987299494},
{"learn":[0.1530438548],"iteration":704,"passed_time":0.9496389447,"remaining_time":0.3973666506},
{"learn":[0.1529570422],"iteration":705,"passed_time":0.9509992011,"remaining_time":0.3960251631},
{"learn":[0.1525699908],"iteration":706,"passed_time":0.9520459638,"remaining_time":0.3945537021},
{"learn":[0.1523757575],"iteration":707,"passed_time":0.9531564697,"remaining_time":0.3931097304},
{"learn":[0.1521109149],"iteration":708,"passed_time":0.954233289,"remaining_time":0.3916528732},
{"learn":[0.1519964094],"iteration":709,"passed_time":0.9553262734,"remaining_time":0.3902036891},
{"learn":[0.1517922826],"iteration":710,"passed_time":0.9563983822,"remaining_time":0.3887470218},
{"learn":[0.1515482288],"iteration":711,"passed_time":0.957458983,"remaining_time":0.3872867797},
{"learn":[0.1513502331],"iteration":712,"passed_time":0.95853222,"remaining_time":0.3858327449},
{"learn":[0.1512665839],"iteration":713,"passed_time":0.9601024947,"remaining_time":0.3845788704},
{"learn":[0.1509611322],"iteration":714,"passed_time":0.9613078991,"remaining_time":0.3831786731},
{"learn":[0.1507799672],"iteration":715,"passed_time":0.9627808051,"remaining_time":0.3818851238},
{"learn":[0.1503399711],"iteration":716,"passed_time":0.963737045,"remaining_time":0.3803871461},
{"learn":[0.150022664],"iteration":717,"passed_time":0.9647134859,"remaining_time":0.3788986114},
{"learn":[0.149787961],"iteration":718,"passed_time":0.9656918254,"remaining_time":0.3774122433},
{"learn":[0.149646689],"iteration":719,"passed_time":0.9666637942,"remaining_time":0.3759248089},
{"learn":[0.149468812],"iteration":720,"passed_time":0.9676482725,"remaining_time":0.374443645},
{"learn":[0.1490485375],"iteration":721,"passed_time":0.9686231621,"remaining_time":0.3729601649},
{"learn":[0.1488756912],"iteration":722,"passed_time":0.9695817667,"remaining_time":0.3714718525},
{"learn":[0.1486842292],"iteration":723,"passed_time":0.9705480786,"remaining_time":0.3699879415},
{"learn":[0.1485136147],"iteration":724,"passed_time":0.9715134083,"remaining_time":0.3685050859},
{"learn":[0.1482825359],"iteration":725,"passed_time":0.9724579581,"remaining_time":0.3670158134},
{"learn":[0.1480308749],"iteration":726,"passed_time":0.9734131802,"remaining_time":0.365532047},
{"learn":[0.1478979515],"iteration":727,"passed_time":0.9744401165,"remaining_time":0.364076527},
{"learn":[0.1476624668],"iteration":728,"passed_time":0.9757631432,"remaining_time":0.3627322521},
{"learn":[0.1473846669],"iteration":729,"passed_time":0.9769186429,"remaining_time":0.3613260734},
{"learn":[0.1471830778],"iteration":730,"passed_time":0.9779735017,"remaining_time":0.3598835458},
{"learn":[0.1469540654],"iteration":731,"passed_time":0.978926372,"remaining_time":0.3584047373},
{"learn":[0.1466852921],"iteration":732,"passed_time":0.9798910939,"remaining_time":0.3569316809},
{"learn":[0.1465152199],"iteration":733,"passed_time":0.9808624567,"remaining_time":0.3554624162},
{"learn":[0.1463138727],"iteration":734,"passed_time":0.9818399233,"remaining_time":0.3539967071},
{"learn":[0.146277929],"iteration":735,"passed_time":0.9828285529,"remaining_time":0.3525363288},
{"learn":[0.1461457262],"iteration":736,"passed_time":0.983768656,"remaining_time":0.3510599139},
{"learn":[0.1458783572],"iteration":737,"passed_time":0.9847254804,"remaining_time":0.3495908887},
{"learn":[0.1457563456],"iteration":738,"passed_time":0.985684892,"remaining_time":0.3481241635},
{"learn":[0.1456294266],"iteration":739,"passed_time":0.9866376165,"remaining_time":0.3466564599},
{"learn":[0.1454379911],"iteration":740,"passed_time":0.9876348013,"remaining_time":0.3452056863},
{"learn":[0.145344281],"iteration":741,"passed_time":0.9886000354,"remaining_time":0.3437450258},
{"learn":[0.1451713263],"iteration":742,"passed_time":0.9895404336,"remaining_time":0.3422771083},
{"learn":[0.1448264492],"iteration":743,"passed_time":0.9912032846,"remaining_time":0.3410591947},
{"learn":[0.1446452448],"iteration":744,"passed_time":0.9924326376,"remaining_time":0.3396917082},
{"learn":[0.1444288164],"iteration":745,"passed_time":0.9935629224,"remaining_time":0.338290861},
{"learn":[0.1443542958],"iteration":746,"passed_time":0.9945176277,"remaining_time":0.3368312715},
{"learn":[0.1441932421],"iteration":747,"passed_time":0.9955070581,"remaining_time":0.3353847308},
{"learn":[0.1440494776],"iteration":748,"passed_time":0.9964692465,"remaining_time":0.3339302815},
{"learn":[0.1439495898],"iteration":749,"passed_time":0.9974431796,"remaining_time":0.3324810599},
{"learn":[0.1436724408],"iteration":750,"passed_time":0.9984304109,"remaining_time":0.3310375131},
{"learn":[0.1434288438],"iteration":751,"passed_time":0.999389973,"remaining_time":0.3295860549},
{"learn":[0.1432980073],"iteration":752,"passed_time":1.000352022,"remaining_time":0.328136719},
{"learn":[0.1430183876],"iteration":753,"passed_time":1.001318965,"remaining_time":0.3266902726},
{"learn":[0.142840009],"iteration":754,"passed_time":1.002275845,"remaining_time":0.3252418305},
{"learn":[0.1426639215],"iteration":755,"passed_time":1.003228259,"remaining_time":0.3237932476},
{"learn":[0.1423996366],"iteration":756,"passed_time":1.004166812,"remaining_time":0.3223415262},
{"learn":[0.1420239248],"iteration":757,"passed_time":1.00516955,"remaining_time":0.3209116506},
{"learn":[0.1416698687],"iteration":758,"passed_time":1.007168602,"remaining_time":0.3197992531},
{"learn":[0.1415158555],"iteration":759,"passed_time":1.008695181,"remaining_time":0.3185353203},
{"learn":[0.1413663999],"iteration":760,"passed_time":1.010435826,"remaining_time":0.317337927},
{"learn":[0.1413243401],"iteration":761,"passed_time":1.011616744,"remaining_time":0.3159642849},
{"learn":[0.1411564048],"iteration":762,"passed_time":1.012998492,"remaining_time":0.314653529},
{"learn":[0.1409487313],"iteration":763,"passed_time":1.014469934,"remaining_time":0.3133702937},
{"learn":[0.1407681423],"iteration":764,"passed_time":1.016069615,"remaining_time":0.3121259602},
{"learn":[0.140619839],"iteration":765,"passed_time":1.017027667,"remaining_time":0.310684692},
{"learn":[0.140315855],"iteration":766,"passed_time":1.017975645,"remaining_time":0.3092416236},
{"learn":[0.1402595],"iteration":767,"passed_time":1.018943901,"remaining_time":0.3078059701},
{"learn":[0.1398625522],"iteration":768,"passed_time":1.019920039,"remaining_time":0.3063738998},
{"learn":[0.1395464228],"iteration":769,"passed_time":1.021006549,"remaining_time":0.3049759822},
{"learn":[0.1392654103],"iteration":770,"passed_time":1.022523576,"remaining_time":0.303706743},
{"learn":[0.1390282442],"iteration":771,"passed_time":1.023756618,"remaining_time":0.3023529908},
{"learn":[0.1388954514],"iteration":772,"passed_time":1.025087999,"remaining_time":0.3010284292},
{"learn":[0.1386439469],"iteration":773,"passed_time":1.026172784,"remaining_time":0.2996318466},
{"learn":[0.1384257962],"iteration":774,"passed_time":1.027468263,"remaining_time":0.2982972376},
{"learn":[0.138213463],"iteration":775,"passed_time":1.028444114,"remaining_time":0.2968704658},
{"learn":[0.1380320097],"iteration":776,"passed_time":1.029420544,"remaining_time":0.2954450209},
{"learn":[0.1379393111],"iteration":777,"passed_time":1.030368693,"remaining_time":0.2940126605},
{"learn":[0.1376842204],"iteration":778,"passed_time":1.031336452,"remaining_time":0.2925871063},
{"learn":[0.1374577262],"iteration":779,"passed_time":1.032295359,"remaining_time":0.2911602295},
{"learn":[0.1372394121],"iteration":780,"passed_time":1.033270297,"remaining_time":0.2897390462},
{"learn":[0.137017262],"iteration":781,"passed_time":1.034214816,"remaining_time":0.2883105241},
{"learn":[0.1368972125],"iteration":782,"passed_time":1.035370796,"remaining_time":0.2869418424},
{"learn":[0.136775967],"iteration":783,"passed_time":1.036385855,"remaining_time":0.2855348785},
{"learn":[0.1365004538],"iteration":784,"passed_time":1.037623554,"remaining_time":0.2841898906},
{"learn":[0.1363563936],"iteration":785,"passed_time":1.038715644,"remaining_time":0.2828055317},
{"learn":[0.1361725463],"iteration":786,"passed_time":1.039866095,"remaining_time":0.2814377106},
{"learn":[0.1360738218],"iteration":787,"passed_time":1.04088151,"remaining_time":0.2800341119},
{"learn":[0.135959265],"iteration":788,"passed_time":1.04189828,"remaining_time":0.2786318593},
{"learn":[0.1356861038],"iteration":789,"passed_time":1.042884674,"remaining_time":0.2772225084},
{"learn":[0.135580497],"iteration":790,"passed_time":1.043895654,"remaining_time":0.2758207228},
{"learn":[0.1354401536],"iteration":791,"passed_time":1.044885902,"remaining_time":0.2744144794},
{"learn":[0.1352237877],"iteration":792,"passed_time":1.045834271,"remaining_time":0.2729983532},
{"learn":[0.1350370488],"iteration":793,"passed_time":1.046843653,"remaining_time":0.2715992348},
{"learn":[0.1348638197],"iteration":794,"passed_time":1.047857611,"remaining_time":0.2702022771},
{"learn":[0.1346539045],"iteration":795,"passed_time":1.048856287,"remaining_time":0.268802365},
{"learn":[0.1345347216],"iteration":796,"passed_time":1.049843048,"remaining_time":0.2674004249},
{"learn":[0.1342351881],"iteration":797,"passed_time":1.050867033,"remaining_time":0.2660089481},
{"learn":[0.1340002381],"iteration":798,"passed_time":1.051927673,"remaining_time":0.2646276122},
{"learn":[0.1338887643],"iteration":799,"passed_time":1.053451826,"remaining_time":0.2633629566},
{"learn":[0.1337142851],"iteration":800,"passed_time":1.054528056,"remaining_time":0.261986371},
{"learn":[0.1334199037],"iteration":801,"passed_time":1.055671453,"remaining_time":0.2606271167},
{"learn":[0.133051787],"iteration":802,"passed_time":1.056688221,"remaining_time":0.2592373343},
{"learn":[0.1329049826],"iteration":803,"passed_time":1.057667276,"remaining_time":0.2578392861},
{"learn":[0.1326541041],"iteration":804,"passed_time":1.058638097,"remaining_time":0.2564402844},
{"learn":[0.132471688],"iteration":805,"passed_time":1.059617689,"remaining_time":0.2550444561},
{"learn":[0.1322759194],"iteration":806,"passed_time":1.060604131,"remaining_time":0.2536512976},
{"learn":[0.1320738147],"iteration":807,"passed_time":1.061590874,"remaining_time":0.2522592176},
{"learn":[0.1317433295],"iteration":808,"passed_time":1.062571912,"remaining_time":0.2508667925},
{"learn":[0.131521075],"iteration":809,"passed_time":1.063568474,"remaining_time":0.2494790247},
{"learn":[0.1313034825],"iteration":810,"passed_time":1.064563317,"remaining_time":0.2480918211},
{"learn":[0.1312643318],"iteration":811,"passed_time":1.065540285,"remaining_time":0.2467014453},
{"learn":[0.1310168337],"iteration":812,"passed_time":1.066509336,"remaining_time":0.2453102655},
{"learn":[0.1308783754],"iteration":813,"passed_time":1.067801111,"remaining_time":0.2439938656},
{"learn":[0.1305736873],"iteration":814,"passed_time":1.069231401,"remaining_time":0.2427089683},
{"learn":[0.1304626276],"iteration":815,"passed_time":1.07054746,"remaining_time":0.2413979566},
{"learn":[0.1303551704],"iteration":816,"passed_time":1.07180314,"remaining_time":0.2400734083},
{"learn":[0.1302274486],"iteration":817,"passed_time":1.073033366,"remaining_time":0.238743365},
{"learn":[0.1299963617],"iteration":818,"passed_time":1.074079386,"remaining_time":0.2373728557},
{"learn":[0.1297324801],"iteration":819,"passed_time":1.075086814,"remaining_time":0.2359946665},
{"learn":[0.1295142609],"iteration":820,"passed_time":1.076125046,"remaining_time":0.2346240965},
{"learn":[0.1293540804],"iteration":821,"passed_time":1.077105573,"remaining_time":0.2332418393},
{"learn":[0.1290849809],"iteration":822,"passed_time":1.078096471,"remaining_time":0.2318627891},
{"learn":[0.1288378368],"iteration":823,"passed_time":1.079134969,"remaining_time":0.2304948478},
{"learn":[0.1287287894],"iteration":824,"passed_time":1.080140667,"remaining_time":0.2291207475},
{"learn":[0.1284592933],"iteration":825,"passed_time":1.081150025,"remaining_time":0.2277483104},
{"learn":[0.1284003556],"iteration":826,"passed_time":1.082187341,"remaining_time":0.2263825998},
{"learn":[0.1282862849],"iteration":827,"passed_time":1.083246434,"remaining_time":0.225022206},
{"learn":[0.1279662214],"iteration":828,"passed_time":1.084700849,"remaining_time":0.2237440835},
{"learn":[0.1278187519],"iteration":829,"passed_time":1.086098874,"remaining_time":0.2224539862},
{"learn":[0.127662139],"iteration":830,"passed_time":1.087229016,"remaining_time":0.22110915},
{"learn":[0.1275643826],"iteration":831,"passed_time":1.088235176,"remaining_time":0.2197397952},
{"learn":[0.1274738925],"iteration":832,"passed_time":1.089290764,"remaining_time":0.2183812217},
{"learn":[0.1272576025],"iteration":833,"passed_time":1.090376853,"remaining_time":0.2170294456},
{"learn":[0.1271184825],"iteration":834,"passed_time":1.09148386,"remaining_time":0.2156824395},
{"learn":[0.1268523302],"iteration":835,"passed_time":1.092581117,"remaining_time":0.2143340948},
{"learn":[0.1268179796],"iteration":836,"passed_time":1.093683177,"remaining_time":0.2129872854},
{"learn":[0.1267241117],"iteration":837,"passed_time":1.094791037,"remaining_time":0.2116421814},
{"learn":[0.1264329792],"iteration":838,"passed_time":1.095884414,"remaining_time":0.2102948637},
{"learn":[0.126342218],"iteration":839,"passed_time":1.096972879,"remaining_time":0.2089472151},
{"learn":[0.126090865],"iteration":840,"passed_time":1.098104155,"remaining_time":0.2076082766},
{"learn":[0.125805181],"iteration":841,"passed_time":1.09965872,"remaining_time":0.2063492611},
{"learn":[0.1256529851],"iteration":842,"passed_time":1.100759948,"remaining_time":0.2050051149},
{"learn":[0.1254326378],"iteration":843,"passed_time":1.102153541,"remaining_time":0.2037155833},
{"learn":[0.1251555947],"iteration":844,"passed_time":1.103149553,"remaining_time":0.2023528766},
{"learn":[0.1249320519],"iteration":845,"passed_time":1.104140595,"remaining_time":0.200990132},
{"learn":[0.1247590346],"iteration":846,"passed_time":1.105161235,"remaining_time":0.1996336114},
{"learn":[0.1246261212],"iteration":847,"passed_time":1.106155823,"remaining_time":0.1982732135},
{"learn":[0.124301081],"iteration":848,"passed_time":1.107171656,"remaining_time":0.1969174559},
{"learn":[0.1241303935],"iteration":849,"passed_time":1.108143149,"remaining_time":0.1955546734},
{"learn":[0.1240075231],"iteration":850,"passed_time":1.109154042,"remaining_time":0.1941997089},
{"learn":[0.1239079679],"iteration":851,"passed_time":1.110109945,"remaining_time":0.1928359998},
{"learn":[0.1237765197],"iteration":852,"passed_time":1.111104024,"remaining_time":0.1914798259},
{"learn":[0.1236427867],"iteration":853,"passed_time":1.112096444,"remaining_time":0.1901242164},
{"learn":[0.1235534838],"iteration":854,"passed_time":1.113095325,"remaining_time":0.1887705521},
{"learn":[0.1232645917],"iteration":855,"passed_time":1.114469394,"remaining_time":0.1874808327},
{"learn":[0.1231401367],"iteration":856,"passed_time":1.115754528,"remaining_time":0.1861760765},
{"learn":[0.1229199723],"iteration":857,"passed_time":1.117291369,"remaining_time":0.1849130238},
{"learn":[0.1228178884],"iteration":858,"passed_time":1.118429945,"remaining_time":0.1835839607},
{"learn":[0.1226318413],"iteration":859,"passed_time":1.119811533,"remaining_time":0.1822949008},
{"learn":[0.1225844692],"iteration":860,"passed_time":1.120798224,"remaining_time":0.1809418735},
{"learn":[0.1223602408],"iteration":861,"passed_time":1.121831582,"remaining_time":0.1795971675},
{"learn":[0.1220809306],"iteration":862,"passed_time":1.122799252,"remaining_time":0.1782427549},
{"learn":[0.1218752326],"iteration":863,"passed_time":1.12378573,"remaining_time":0.1768921983},
{"learn":[0.1216884309],"iteration":864,"passed_time":1.124801582,"remaining_time":0.1755470677},
{"learn":[0.1215025783],"iteration":865,"passed_time":1.125812554,"remaining_time":0.1742019426},
{"learn":[0.1214626141],"iteration":866,"passed_time":1.126808676,"remaining_time":0.1728553101},
{"learn":[0.1212952625],"iteration":867,"passed_time":1.127820986,"remaining_time":0.1715119472},
{"learn":[0.1211089849],"iteration":868,"passed_time":1.128831688,"remaining_time":0.1701691037},
{"learn":[0.1209522546],"iteration":869,"passed_time":1.129822298,"remaining_time":0.1688240215},
{"learn":[0.1208975755],"iteration":870,"passed_time":1.130914045,"remaining_time":0.1674947323},
{"learn":[0.1207730209],"iteration":871,"passed_time":1.132073466,"remaining_time":0.1661759216},
{"learn":[0.1205953772],"iteration":872,"passed_time":1.133315157,"remaining_time":0.1648694444},
{"learn":[0.1204093658],"iteration":873,"passed_time":1.134343385,"remaining_time":0.1635323416},
{"learn":[0.1202511447],"iteration":874,"passed_time":1.135367126,"remaining_time":0.1621953038},
{"learn":[0.1200301989],"iteration":875,"passed_time":1.136372873,"remaining_time":0.1608564341},
{"learn":[0.1198214473],"iteration":876,"passed_time":1.137378581,"remaining_time":0.1595183186},
{"learn":[0.1197590781],"iteration":877,"passed_time":1.138362901,"remaining_time":0.1581779885},
{"learn":[0.1194639588],"iteration":878,"passed_time":1.139341267,"remaining_time":0.1568376488},
{"learn":[0.1191896903],"iteration":879,"passed_time":1.140337991,"remaining_time":0.1555006351},
{"learn":[0.1191617235],"iteration":880,"passed_time":1.141343373,"remaining_time":0.1541655635},
{"learn":[0.1190525005],"iteration":881,"passed_time":1.142324645,"remaining_time":0.1528280137},
{"learn":[0.1187833763],"iteration":882,"passed_time":1.143320543,"remaining_time":0.1514932089},
{"learn":[0.1185794779],"iteration":883,"passed_time":1.144307665,"remaining_time":0.1501580194},
{"learn":[0.1183594553],"iteration":884,"passed_time":1.145326073,"remaining_time":0.1488276818},
{"learn":[0.1181368597],"iteration":885,"passed_time":1.146349498,"remaining_time":0.1474986938},
{"learn":[0.118120575],"iteration":886,"passed_time":1.147806563,"remaining_time":0.1462256388},
{"learn":[0.1180176466],"iteration":887,"passed_time":1.149307672,"remaining_time":0.1449577244},
{"learn":[0.1177574869],"iteration":888,"passed_time":1.150679707,"remaining_time":0.1436731692},
{"learn":[0.1176231818],"iteration":889,"passed_time":1.152046739,"remaining_time":0.1423877992},
{"learn":[0.1174781139],"iteration":890,"passed_time":1.153566852,"remaining_time":0.141120973},
{"learn":[0.11720148],"iteration":891,"passed_time":1.155041689,"remaining_time":0.1398480969},
{"learn":[0.1170050021],"iteration":892,"passed_time":1.156717896,"remaining_time":0.1385988969},
{"learn":[0.1169180285],"iteration":893,"passed_time":1.157725419,"remaining_time":0.1372694569},
{"learn":[0.1166627506],"iteration":894,"passed_time":1.158727056,"remaining_time":0.1359400456},
{"learn":[0.1165645598],"iteration":895,"passed_time":1.159706073,"remaining_time":0.1346087406},
{"learn":[0.1163251926],"iteration":896,"passed_time":1.160743823,"remaining_time":0.1332849652},
{"learn":[0.116077874],"iteration":897,"passed_time":1.162034669,"remaining_time":0.1319905749},
{"learn":[0.1159577157],"iteration":898,"passed_time":1.1630895,"remaining_time":0.1306696769},
{"learn":[0.1157856412],"iteration":899,"passed_time":1.164083812,"remaining_time":0.1293426458},
{"learn":[0.1156139636],"iteration":900,"passed_time":1.165096115,"remaining_time":0.1280183301},
{"learn":[0.1154758595],"iteration":901,"passed_time":1.166133104,"remaining_time":0.1266973882},
{"learn":[0.1154134292],"iteration":902,"passed_time":1.167112994,"remaining_time":0.1253709417},
{"learn":[0.1152459125],"iteration":903,"passed_time":1.16809798,"remaining_time":0.1240458032},
{"learn":[0.1151645556],"iteration":904,"passed_time":1.169111421,"remaining_time":0.1227244034},
{"learn":[0.1149894642],"iteration":905,"passed_time":1.170106854,"remaining_time":0.1214018149},
{"learn":[0.1149107572],"iteration":906,"passed_time":1.17129557,"remaining_time":0.1200997663},
{"learn":[0.11474247],"iteration":907,"passed_time":1.172317093,"remaining_time":0.118781027},
{"learn":[0.1145896458],"iteration":908,"passed_time":1.173326971,"remaining_time":0.1174617759},
{"learn":[0.1143421173],"iteration":909,"passed_time":1.174345998,"remaining_time":0.1161441097},
{"learn":[0.1141081968],"iteration":910,"passed_time":1.175372875,"remaining_time":0.114827866},
{"learn":[0.113907722],"iteration":911,"passed_time":1.176522319,"remaining_time":0.1135240835},
{"learn":[0.1137989027],"iteration":912,"passed_time":1.177557227,"remaining_time":0.1122097248},
{"learn":[0.1136946088],"iteration":913,"passed_time":1.178559557,"remaining_time":0.1108929124},
{"learn":[0.1135169445],"iteration":914,"passed_time":1.17963113,"remaining_time":0.1095832197},
{"learn":[0.1134583191],"iteration":915,"passed_time":1.1806477,"remaining_time":0.108269003},
{"learn":[0.1133720635],"iteration":916,"passed_time":1.181653479,"remaining_time":0.1069544588},
{"learn":[0.1132576286],"iteration":917,"passed_time":1.182716358,"remaining_time":0.1056456877},
{"learn":[0.113152978],"iteration":918,"passed_time":1.183746305,"remaining_time":0.1043345492},
{"learn":[0.1129548865],"iteration":919,"passed_time":1.184734472,"remaining_time":0.1030203889},
{"learn":[0.1128035152],"iteration":920,"passed_time":1.185693641,"remaining_time":0.1017044492},
{"learn":[0.1126863521],"iteration":921,"passed_time":1.186633845,"remaining_time":0.1003876789},
{"learn":[0.1125518501],"iteration":922,"passed_time":1.18756277,"remaining_time":0.09907078365},
{"learn":[0.1124881272],"iteration":923,"passed_time":1.188477204,"remaining_time":0.09775353624},
{"learn":[0.1124073108],"iteration":924,"passed_time":1.189389767,"remaining_time":0.09643700816},
{"learn":[0.1122909692],"iteration":925,"passed_time":1.190351553,"remaining_time":0.09512528613},
{"learn":[0.1121077618],"iteration":926,"passed_time":1.191297115,"remaining_time":0.0938130414},
{"learn":[0.1118899919],"iteration":927,"passed_time":1.192229461,"remaining_time":0.09250056165},
{"learn":[0.1117884032],"iteration":928,"passed_time":1.193142621,"remaining_time":0.0911874339},
{"learn":[0.1116087911],"iteration":929,"passed_time":1.194051262,"remaining_time":0.08987482617},
{"learn":[0.1114042495],"iteration":930,"passed_time":1.194967654,"remaining_time":0.0885636607},
{"learn":[0.1111993393],"iteration":931,"passed_time":1.195893136,"remaining_time":0.08725400566},
{"learn":[0.1109598185],"iteration":932,"passed_time":1.196808698,"remaining_time":0.0859444617},
{"learn":[0.110775146],"iteration":933,"passed_time":1.19772598,"remaining_time":0.08463588294},
{"learn":[0.1106025856],"iteration":934,"passed_time":1.198658215,"remaining_time":0.08332918073},
{"learn":[0.1104722334],"iteration":935,"passed_time":1.199577552,"remaining_time":0.08202239673},
{"learn":[0.1103657641],"iteration":936,"passed_time":1.200493243,"remaining_time":0.08071619454},
{"learn":[0.1101662028],"iteration":937,"passed_time":1.201407344,"remaining_time":0.07941071993},
{"learn":[0.1100370678],"iteration":938,"passed_time":1.202321725,"remaining_time":0.07810609715},
{"learn":[0.1099475672],"iteration":939,"passed_time":1.203258439,"remaining_time":0.07680373015},
{"learn":[0.1097419805],"iteration":940,"passed_time":1.204178274,"remaining_time":0.075501082},
{"learn":[0.1096142882],"iteration":941,"passed_time":1.205280912,"remaining_time":0.07421050199},
{"learn":[0.1094409284],"iteration":942,"passed_time":1.206204272,"remaining_time":0.07290948407},
{"learn":[0.1092256755],"iteration":943,"passed_time":1.207136199,"remaining_time":0.07160977453},
{"learn":[0.1091249148],"iteration":944,"passed_time":1.208049148,"remaining_time":0.0703097388},
{"learn":[0.10890177],"iteration":945,"passed_time":1.208978874,"remaining_time":0.06901147907},
{"learn":[0.1088081205],"iteration":946,"passed_time":1.209902676,"remaining_time":0.06771366614},
{"learn":[0.1086922036],"iteration":947,"passed_time":1.210823414,"remaining_time":0.06641647416},
{"learn":[0.1085890061],"iteration":948,"passed_time":1.211755107,"remaining_time":0.06512066436},
{"learn":[0.1083689566],"iteration":949,"passed_time":1.212687073,"remaining_time":0.06382563543},
{"learn":[0.1081147665],"iteration":950,"passed_time":1.213619829,"remaining_time":0.06253141073},
{"learn":[0.1080323029],"iteration":951,"passed_time":1.214545759,"remaining_time":0.06123760131},
{"learn":[0.1079377036],"iteration":952,"passed_time":1.21546552,"remaining_time":0.05994425966},
{"learn":[0.1077835423],"iteration":953,"passed_time":1.216375307,"remaining_time":0.05865122025},
{"learn":[0.1076719759],"iteration":954,"passed_time":1.217302726,"remaining_time":0.05735981431},
{"learn":[0.1076410423],"iteration":955,"passed_time":1.218234747,"remaining_time":0.05606938166},
{"learn":[0.1074452316],"iteration":956,"passed_time":1.219200043,"remaining_time":0.05478119315},
{"learn":[0.1072307038],"iteration":957,"passed_time":1.220127631,"remaining_time":0.05349202558},
{"learn":[0.1071168046],"iteration":958,"passed_time":1.221046532,"remaining_time":0.05220324067},
{"learn":[0.1070438879],"iteration":959,"passed_time":1.221951471,"remaining_time":0.05091464463},
{"learn":[0.1068961521],"iteration":960,"passed_time":1.222850736,"remaining_time":0.04962661676},
{"learn":[0.1068494081],"iteration":961,"passed_time":1.223761062,"remaining_time":0.04833983404},
{"learn":[0.1066601998],"iteration":962,"passed_time":1.22469647,"remaining_time":0.04705479689},
{"learn":[0.1064505688],"iteration":963,"passed_time":1.225624438,"remaining_time":0.04577020721},
{"learn":[0.1063241191],"iteration":964,"passed_time":1.226555919,"remaining_time":0.04448648413},
{"learn":[0.1062287347],"iteration":965,"passed_time":1.227490528,"remaining_time":0.04320360035},
{"learn":[0.1060398416],"iteration":966,"passed_time":1.228414484,"remaining_time":0.0419210734},
{"learn":[0.1059879369],"iteration":967,"passed_time":1.229358874,"remaining_time":0.04063996277},
{"learn":[0.1058175258],"iteration":968,"passed_time":1.230293645,"remaining_time":0.03935923941},
{"learn":[0.1056505551],"iteration":969,"passed_time":1.231213536,"remaining_time":0.03807876915},
{"learn":[0.1054776927],"iteration":970,"passed_time":1.232132049,"remaining_time":0.03679900044},
{"learn":[0.1053358183],"iteration":971,"passed_time":1.233056302,"remaining_time":0.03552014039},
{"learn":[0.1052182194],"iteration":972,"passed_time":1.234130458,"remaining_time":0.03424616892},
{"learn":[0.1051328123],"iteration":973,"passed_time":1.235064273,"remaining_time":0.03296886149},
{"learn":[0.1050133539],"iteration":974,"passed_time":1.23598054,"remaining_time":0.03169180872},
{"learn":[0.1048840596],"iteration":975,"passed_time":1.236889575,"remaining_time":0.03041531743},
{"learn":[0.1046805134],"iteration":976,"passed_time":1.237822858,"remaining_time":0.02914014916},
{"learn":[0.1044987639],"iteration":977,"passed_time":1.238764517,"remaining_time":0.02786586849},
{"learn":[0.1042554953],"iteration":978,"passed_time":1.239685079,"remaining_time":0.02659181477},
{"learn":[0.1041763942],"iteration":979,"passed_time":1.240607879,"remaining_time":0.02531852814},
{"learn":[0.1039981865],"iteration":980,"passed_time":1.241557548,"remaining_time":0.02404647647},
{"learn":[0.1038101763],"iteration":981,"passed_time":1.242477544,"remaining_time":0.02277453746},
{"learn":[0.1037107823],"iteration":982,"passed_time":1.243383112,"remaining_time":0.02150306501},
{"learn":[0.103596285],"iteration":983,"passed_time":1.24431365,"remaining_time":0.02023274228},
{"learn":[0.1034598898],"iteration":984,"passed_time":1.245216736,"remaining_time":0.01896269141},
{"learn":[0.1033291108],"iteration":985,"passed_time":1.246135203,"remaining_time":0.01769360329},
{"learn":[0.1032803201],"iteration":986,"passed_time":1.247054289,"remaining_time":0.0164252338},
{"learn":[0.1031867829],"iteration":987,"passed_time":1.247961631,"remaining_time":0.01515742872},
{"learn":[0.1030134372],"iteration":988,"passed_time":1.249032144,"remaining_time":0.01389216743},
{"learn":[0.1028997881],"iteration":989,"passed_time":1.249968043,"remaining_time":0.01262593983},
{"learn":[0.1027446805],"iteration":990,"passed_time":1.250886346,"remaining_time":0.01136021909},
{"learn":[0.1026690632],"iteration":991,"passed_time":1.251811609,"remaining_time":0.01009525491},
{"learn":[0.1026108162],"iteration":992,"passed_time":1.252735682,"remaining_time":0.008830966539},
{"learn":[0.1025313918],"iteration":993,"passed_time":1.253654878,"remaining_time":0.007567333265},
{"learn":[0.1024492367],"iteration":994,"passed_time":1.254565623,"remaining_time":0.006304349863},
{"learn":[0.1023756968],"iteration":995,"passed_time":1.255492543,"remaining_time":0.005042138725},
{"learn":[0.102307436],"iteration":996,"passed_time":1.25641535,"remaining_time":0.003780587814},
{"learn":[0.1021506126],"iteration":997,"passed_time":1.257344013,"remaining_time":0.002519727481},
{"learn":[0.1019756303],"iteration":998,"passed_time":1.258280086,"remaining_time":0.001259539626},
{"learn":[0.1018080646],"iteration":999,"passed_time":1.259200371,"remaining_time":0}
]}